testing/HoloRiscV.v
/*

This version of the core will use a 32 bit bus for address and 8 bit bus for data, along with separate instruction and data memories. It will implement the RV32I architecture.

NOTE: This version is not meant for implementation. It is the active development version meant to be run in a testbench.

*/

`timescale 1ns/100ps
`default_nettype none

module HoloRiscV (

	);
	
	reg [7:0] instr_mem [0:3];
	reg [7:0] prog_mem [0:15];
	//reg [31:0] reg_init [0:31];

	initial begin
		$dumpfile("HoloRiscV.vcd");
		$dumpvars(0,HoloRiscV);
		$readmemb("instr.mem",instr_mem);
		$readmemb("prog.mem",prog_mem);
		//$readmemb("reg.mem",REG_FILE);
		#1000 $finish;
	end

	reg clk = 0;

	always #10 clk = !clk;

	//Define stages
	parameter FETCH = 3'b000;
	parameter DECODE = 3'b001;
	parameter EXECUTE = 3'b010;
	parameter MEMORY = 3'b011;
	parameter WRITEBACK = 3'b100;

	//Define ALUI operations
	parameter ADDI = 3'b000;
	parameter SLTI = 3'b010;
	parameter SLTIU = 3'b011;
	parameter XORI = 3'b100;
	parameter ORI = 3'b110;
	parameter ANDI = 3'b111;
	parameter SLLI = 3'b001;
	parameter SRI = 3'b101;
	
	//Define ALU operations
	parameter ADD = 3'b000;
	parameter SLL = 3'b001;
	parameter SLT = 3'b010;
	parameter SLTU = 3'b011;
	parameter XOR = 3'b100;
	parameter SR = 3'b101;
	parameter OR = 3'b110;
	parameter AND = 3'b111;

	//Define branches
	parameter BEQ = 3'b000;
	parameter BNE = 3'b001;
	parameter BLT = 3'b100;
	parameter BGE = 3'b101;
	parameter BLTU = 3'b110;
	parameter BGEU = 3'b111;

	//Define load operations
	parameter LB = 3'b000;
	parameter LH = 3'b001;
	parameter LW = 3'b010;
	parameter LBU = 3'b100;
	parameter LHU = 3'b101;
	
	//Define store operations
	parameter SB = 3'b000;
	parameter SH = 3'b001;
	parameter SW = 3'b010;

	//Define instruction formats
	parameter R = 3'b001;
	parameter I = 3'b010;
	parameter S = 3'b011;
	parameter B = 3'b100;
	parameter U = 3'b101;
	parameter J = 3'b110;

	//Define opcodes
	parameter LUI = 7'b0110111;
	parameter AUIPC = 7'b0010111;
	parameter JAL = 7'b1101111;
	parameter JALR = 7'b1100111;
	parameter BRANCH = 7'b1100011;
	parameter LOAD = 7'b0000011;
	parameter STORE = 7'b0100011;
	parameter ALUI = 7'b0010011;
	parameter ALU = 7'b0110011;

	//Instruction memory I/O
	reg [1:0] INSTR_ADDR;
	reg [7:0] INSTR_DATA;
	reg INSTR_OE = 1;
	
	//Program memory I/O
	reg [31:0] DATA_ADDR;
	reg [7:0] DATA_OUT;
	reg [7:0] DATA_IN;
	reg DATA_OE = 0;
	reg DATA_WE = 0;

	//Registers
	reg [31:0] CMD = 0;
	reg [31:0] REG_FILE [0:31];
	reg [31:0] PC = 0;

	//Control registers
	reg [2:0] STAGE = 0;
	reg [3:0] CYCLE = 4'b0000;
	reg [3:0] SCYCLE = 4'b0000;
	reg [2:0] TYPE;

	//Intermediate registers
	reg [4:0] RD = 0;
	reg [2:0] F3 = 0;
	reg [4:0] RS1 = 0;
	reg [4:0] RS2 = 0;
	reg [6:0] F7 = 0;
	reg [31:0] IMM = 0;
	reg [31:0] TMP = 0;
	reg [31:0] SRC1 = 0;
	reg [31:0] SRC2 = 0;
	reg [31:0] DEST = 0;
	reg [31:0] EXTENDED = 0;

	reg [7:0] INSTR = 0;

	always @(posedge clk) begin
		REG_FILE[0] <= 0;
		//FETCH
		if (STAGE == FETCH) begin
			case (CYCLE)
				0 : begin
					INSTR_ADDR <= PC[1:0];
					CYCLE <= 1;
				end
				1 : begin
					CMD[31:24] <= instr_mem[INSTR_ADDR];
					CYCLE <= 2;
				end
				2 : begin
					INSTR_ADDR <= INSTR_ADDR + 1;
					CYCLE <= 3;
				end
				3 : begin
					CMD[23:16] <= instr_mem[INSTR_ADDR];
					CYCLE <= 4;
				end
				4 : begin
					INSTR_ADDR <= INSTR_ADDR + 1;
					CYCLE <= 5;
				end
				5 : begin
					CMD[15:8] <= instr_mem[INSTR_ADDR];
					CYCLE <= 6;
				end
				6 : begin
					INSTR_ADDR <= INSTR_ADDR + 1;
					CYCLE <= 7;
				end
				7 : begin
					CMD[7:0] <= instr_mem[INSTR_ADDR];
					CYCLE <= 8;
				end
				8 : begin
					CYCLE <= 0;
					STAGE <= DECODE;
					INSTR_ADDR <= PC[1:0];
					REG_FILE[1] <= -13;
					REG_FILE[2] <= 4;
				end
				default : begin
				end
			endcase
		end
		//DECODE
		if (STAGE == DECODE) begin
			case (CYCLE)
				0 : begin
					case (CMD[6:0])
						LUI : TYPE <= U;
						AUIPC : TYPE <= U;
						JAL : TYPE <= J;
						JALR : TYPE <= I;
						BRANCH : TYPE <= B;
						LOAD : TYPE <= I;
						STORE : TYPE <= S;
						ALUI : begin
							case (CMD[14:12])
								3'b001 : TYPE <= R;
								3'b101 : TYPE <= R;
								default : TYPE <= I;
							endcase
						end
						ALU : TYPE <= R;
						default : begin
						end
					endcase
					CYCLE <= 1;
				end
				1 : begin
					case (TYPE)
						R : begin //R
							F7 <= CMD[31:25];
							RS2 <= CMD[24:20];
							RS1 <= CMD[19:15];
							F3 <= CMD[14:12];
							RD <= CMD[11:7];
						end
						I : begin //I
							IMM[11:0] <= CMD[31:20];
							RS1 <= CMD[19:15];
							F3 <= CMD[14:12];
							RD <= CMD[11:7];
							EXTENDED <= {{20{CMD[31]}},IMM[31:20]};
						end
						S : begin //S
							IMM[11:0] <= {CMD[31:25],CMD[11:7]};
							RS2 <= CMD[24:20];
							RS1 <= CMD[19:15];
							F3 <= CMD[14:12];
						end
						B : begin //B
							IMM[11:0] <= {CMD[31],CMD[7],CMD[30:25],CMD[11:8]};
							RS2 <= CMD[24:20];
							RS1 <= CMD[19:15];
							F3 <= CMD[14:12];
						end
						U : begin //U
							IMM[31:12] <= CMD[31:12];
							RD <= CMD[11:7];
						end
						J : begin //J
							IMM[20:1] <= {CMD[31],CMD[19:12],CMD[20],CMD[30:21]};
							RD <= CMD[11:7];
							EXTENDED <= {{20{CMD[31]}},IMM[31:20]};
						end
						default : begin
						end
					endcase
					CYCLE <= 2;
				end
				2 : begin
					case (TYPE)
						R : begin
							SRC2 <= REG_FILE[RS2];
							SRC1 <= REG_FILE[RS1];
							//SRC1 <= {1'b1,31'b110000000};
							//SRC2 <= 32'b1110010;
						end
						I : begin
							SRC1 <= REG_FILE[RS1];
							//SRC1 <= {1'b0,7'b1,24'b0};
							//SRC1 <= {22'b111111111,10'b1111100};
						end
						S : begin
							SRC2 <= REG_FILE[RS2];
							SRC1 <= REG_FILE[RS1];
						end
						B : begin
							SRC2 <= REG_FILE[RS2];
							SRC1 <= REG_FILE[RS1];
						end
						default : begin
						end
					endcase
					CYCLE <= 3;
				end
				3 : begin
					CYCLE <= 0;
					STAGE <= EXECUTE;
					//STAGE <= FETCH;
					//PC <= PC + 4;
				end
			endcase
		end
		//EXECUTE
		if (STAGE == EXECUTE) begin
			case (CYCLE)
				0 : begin
					case (CMD[6:0])
						LUI : begin //FUNCTIONAL
							DEST <= {IMM[31:12],{12{1'b0}}};
							CYCLE <= 1;
						end
						AUIPC : begin //FUNCTIONAL
							DEST <= PC + {IMM[31:12],{12{1'b0}}};
							CYCLE <= 1;
						end
						JAL : begin //PROBLEM LOCATED
							case (SCYCLE)
								0: begin
									PC <= PC + {{12{IMM[20]}},IMM[20:1]};
									SCYCLE <= 1;
								end
								1 : begin
									DEST <= PC + 4;
									CYCLE <= 1;
									SCYCLE <= 0;
								end
								default : begin
								end
							endcase	
						end
						JALR : begin //PROBLEM LOCATED
							case (SCYCLE)
								0 : begin
									PC <= SRC1 + {{20{IMM[11]}},IMM[11:0]};
									SCYCLE <= 1;
								end
								1 : begin
									PC[0] <= 1'b0;
									SCYCLE <= 2;
								end
								2 : begin
									PC <= PC + 4;
									SCYCLE <= 3;
									CYCLE <= 1;
								end
								3 : begin
									//STAGE <= MEMORY;
									SCYCLE <= 0;
									CYCLE <= 1;
								end
								default : begin
								end
							endcase
						end
						BRANCH : begin //UNTESTED DUE TO HIGH CHANCE OF PROBLEMS
							case (F3)
								BEQ : begin
									if (SRC1 == SRC2) begin
										PC <= PC + {{20{IMM[12]}},IMM[12:1]};
									end
								end
								BNE : begin
									if (SRC1 != SRC2) begin
										PC <= PC + {{20{IMM[12]}},IMM[12:1]};
									end
								end
								BLT : begin
									if ($signed(SRC1) < $signed(SRC2)) begin
										PC <= PC + {{20{IMM[12]}},IMM[12:1]};
									end
								end
								BGE : begin
									if ($signed(SRC1) >= $signed(SRC2)) begin
										PC <= PC + {{20{IMM[12]}},IMM[12:1]};
									end
								end
								BLTU : begin
									if (SRC1 < SRC2) begin
										PC <= PC + {{20{IMM[12]}},IMM[12:1]};
									end
								end
								BGEU : begin
									if (SRC1 >= SRC2) begin
										PC <= PC + {{20{IMM[12]}},IMM[12:1]};
									end
								end
								default : begin
								end
							endcase
							CYCLE <= 1;
						end
						ALUI : begin //FUNCTIONAL
							case (F3)
								ADDI : begin //FUNCTIONAL
									DEST <= SRC1 + EXTENDED;
									CYCLE <= 1;
								end
								SLTI : begin //FUNCTIONAL
									if ($signed(SRC1) < $signed(EXTENDED)) begin
										DEST <= 1;
									end
									else begin
										DEST <= 0;
									end
									CYCLE <= 1;
								end
								SLTIU : begin //FUNCTIONAL
									if (SRC1 < EXTENDED) begin
										DEST <= 1;
									end
									else begin
										DEST <= 0;
									end
									CYCLE <= 1;
								end
								XORI : begin //FUNCTIONAL
									//DEST <= SRC1 ^ {{20{IMM[11]}},IMM[11:0]};
									DEST <= SRC1 ^ EXTENDED;
									CYCLE <= 1;
								end
								ORI : begin //FUNCTIONAL
									//DEST <= SRC1 | {{20{IMM[11]}},IMM[11:0]};
									DEST <= SRC1 | EXTENDED;
									CYCLE <= 1;
								end
								ANDI : begin //FUNCTIONAL
									//DEST <= SRC1 & {{20{IMM[11]}},IMM[11:0]};
									DEST <= SRC1 ^ EXTENDED;
									CYCLE <= 1;
								end
								SLLI : begin //FUNCTIONAL
									DEST <= SRC1 << CMD[24:20];
									CYCLE <= 1;
								end
								SRI : begin //FUNCTIONAL
									case (CMD[30])
										0 : begin
											DEST <= SRC1 >> CMD[24:20];
										end
										1 : begin
											DEST <= $signed(SRC1) >>> CMD[24:20];
										end
									endcase
									CYCLE <= 1;
								end
							endcase
						end
						ALU : begin //FUNCTIONAL
							case (F3)
								ADD : begin //FUNCTIONAL
									case (CMD[30])
										0 : begin
											DEST <= SRC1 + SRC2;
										end
										1 : begin
											DEST <= SRC1 - SRC2;
										end
									endcase
									CYCLE <= 1;
								end
								SLL : begin //FUNCTIONAL
									DEST <= SRC1 << SRC2[4:0];
									CYCLE <= 1;
								end
								SLT : begin //FUNCTIONAL
									if ($signed(SRC1) < $signed(SRC2)) begin
										DEST <= 1;
									end
									else begin
										DEST <= 0;
									end
									CYCLE <= 1;
								end
								SLTU : begin //FUNCTIONAL
									if (SRC1 < SRC2) begin
										DEST <= 1;
									end
									else begin
										DEST <= 0;
									end
									CYCLE <= 1;
								end
								XOR : begin //FUNCTIONAL
									DEST <= SRC1 ^ SRC2;
									CYCLE <= 1;
								end
								SR : begin //FUNCTIONAL
									case (CMD[30])
										0 : begin
											DEST <= SRC1 >> SRC2[4:0];
										end
										1 : begin
											DEST <= $signed(SRC1) >>> SRC2[4:0];
										end
									endcase
									CYCLE <= 1;
								end
								OR : begin //FUNCTIONAL
									DEST <= SRC1 | SRC2;
									CYCLE <= 1;
								end
								AND : begin //FUNCTIONAL
									DEST <= SRC1 & SRC2;
									CYCLE <= 1;
								end
							endcase
						end
						LOAD : CYCLE <= 1;
						STORE : CYCLE <= 1;
						default : begin
							CYCLE <= 1;
						end
					endcase
				end
				1 : begin
					STAGE <= MEMORY;
					CYCLE <= 0;
					SCYCLE <= 0;
				end
			endcase
		end
		//MEMORY
		if (STAGE == MEMORY) begin //BROKEN
			DATA_IN <= prog_mem[DATA_ADDR];
			case (CYCLE)
				0 : begin
					case (CMD[6:0])
						LOAD : begin
							DATA_WE <= 0;
							DATA_OE <= 1;
						end
						STORE : begin
							DATA_OE <= 0;
							DATA_WE <= 1;
						end
						default : begin
						end
					endcase
					CYCLE <= 1;
				end
				1 : begin
					//DATA_ADDR <= SRC1 + {{20{IMM[11]}},IMM[11:0]};
					DATA_ADDR <= SRC1;
					CYCLE <= 2;
				end
				2 : begin
					CYCLE <= 3;
				end
				3 : begin
					case (CMD[6:0])
						LOAD : begin
							case (F3)
								LB : begin
									DEST <= {{24{DATA_IN[7]}},DATA_IN};
									CYCLE <= 4;
								end
								LH : begin
									case (SCYCLE)
										0 : begin
											DEST[7:0] <= DATA_IN;
											SCYCLE <= 1;
										end
										1 : begin
											DATA_ADDR <= DATA_ADDR + 1;
											SCYCLE <= 2;
										end
										2 : begin
											DEST[31:8] <= {{16{DATA_IN[7]}},DATA_IN};
											SCYCLE <= 0;
											CYCLE <= 4;
										end
										default : begin
										end
									endcase
								end
								LW : begin
									case (SCYCLE)
										0 : begin
											DEST[7:0] <= DATA_IN;
											SCYCLE <= 1;
										end
										1 : begin
											DATA_ADDR <= DATA_ADDR + 1;
											SCYCLE <= 2;
										end
										2 : begin
											DEST[15:8] <= DATA_IN;
											SCYCLE <= 3;
										end
										3 : begin
											DATA_ADDR <= DATA_ADDR + 1;
											SCYCLE <= 4;
										end
										4 : begin
											DEST[23:16] <= DATA_IN;
											SCYCLE <= 5;
										end
										5 : begin
											DATA_ADDR <= DATA_ADDR + 1;
											SCYCLE <= 6;
										end
										6 : begin
											DEST[31:24] <= DATA_IN;
											SCYCLE <= 0;
											CYCLE <= 4;
										end
										default : begin
										end
									endcase
								end
								LBU : begin
									DEST <= {{24{1'b0}},DATA_IN};
									CYCLE <= 4;
								end
								LHU : begin
									case (SCYCLE)
										0 : begin
											DEST[7:0] <= DATA_IN;
											SCYCLE <= 1;
										end
										1 : begin
											DATA_ADDR <= DATA_ADDR + 1;
											SCYCLE <= 2;
										end
										2 : begin
											DEST[31:8] <= {{16{1'b0}},DATA_IN};
											CYCLE <= 4;
											SCYCLE <= 0;
										end
										default : begin
										end
									endcase
								end
								default : begin
								end
							endcase
						end
						STORE : begin
							case (F3)
								SB : begin
									DATA_OUT <= SRC2[7:0];
									CYCLE <= 4;
								end
								SH : begin
									case (SCYCLE)
										0 : begin
											DATA_OUT <= SRC2[7:0];
											SCYCLE <= 1;
										end
										1 : begin
											DATA_ADDR <= DATA_ADDR + 1;
											SCYCLE <= 2;
										end
										2 : begin
											DATA_OUT <= SRC2[15:8];
											SCYCLE <= 0;
											CYCLE <= 4;
										end
										default : begin
										end
									endcase
								end
								SW : begin
									case (SCYCLE)
										0 : begin
											DATA_OUT <= SRC2[7:0];
											SCYCLE <= 1;
										end
										1 : begin
											DATA_ADDR <= DATA_ADDR + 1;
											SCYCLE <= 2;
										end
										2 : begin
											DATA_OUT <= SRC2[15:8];
											SCYCLE <= 3;
										end
										3 : begin
											DATA_ADDR <= DATA_ADDR + 1;
											SCYCLE <= 4;
										end
										4 : begin
											DATA_OUT <= SRC2[23:16];
											SCYCLE <= 5;
										end
										5 : begin
											DATA_ADDR <= DATA_ADDR + 1;
											SCYCLE <= 6;
										end
										6 : begin
											DATA_OUT <= SRC2[31:24];
											SCYCLE <= 0;
											CYCLE <= 4;
										end
										default : begin
										end
									endcase
								end
								default : begin
								end
							endcase
						end
						default : begin
							CYCLE <= 4;
						end
					endcase
				end
				4 : begin
					STAGE <= WRITEBACK;
					CYCLE <= 0;
					SCYCLE <= 0;
					DATA_OE <= 0;
					DATA_WE <= 0;
				end
			endcase
		end
		//WRITEBACK
		if (STAGE == WRITEBACK) begin //FUNCTIONAL
			case (CYCLE)
				0 : begin
					REG_FILE[RD] <= DEST;
					PC <= PC + 4;
					INSTR <= INSTR + 1;
					CYCLE <= 1;
				end
				1 : begin
					CYCLE <= 0;
					STAGE <= FETCH;
				end
				default : begin
				end
			endcase
		end
	end
endmodule

testing/HoloRiscV.vcd
$date
	Fri Mar 19 13:53:33 2021
$end
$version
	Icarus Verilog
$end
$timescale
	100ps
$end
$scope module HoloRiscV $end
$var reg 32 ! CMD [31:0] $end
$var reg 4 " CYCLE [3:0] $end
$var reg 32 # DATA_ADDR [31:0] $end
$var reg 8 $ DATA_IN [7:0] $end
$var reg 1 % DATA_OE $end
$var reg 8 & DATA_OUT [7:0] $end
$var reg 1 ' DATA_WE $end
$var reg 32 ( DEST [31:0] $end
$var reg 32 ) EXTENDED [31:0] $end
$var reg 3 * F3 [2:0] $end
$var reg 7 + F7 [6:0] $end
$var reg 32 , IMM [31:0] $end
$var reg 8 - INSTR [7:0] $end
$var reg 2 . INSTR_ADDR [1:0] $end
$var reg 1 / INSTR_OE $end
$var reg 32 0 PC [31:0] $end
$var reg 5 1 RD [4:0] $end
$var reg 5 2 RS1 [4:0] $end
$var reg 5 3 RS2 [4:0] $end
$var reg 4 4 SCYCLE [3:0] $end
$var reg 32 5 SRC1 [31:0] $end
$var reg 32 6 SRC2 [31:0] $end
$var reg 3 7 STAGE [2:0] $end
$var reg 32 8 TMP [31:0] $end
$var reg 3 9 TYPE [2:0] $end
$var reg 1 : clk $end
$upscope $end
$enddefinitions $end
#0
$dumpvars
0:
bx 9
b0 8
b0 7
b0 6
b0 5
b0 4
b0 3
b0 2
b0 1
b0 0
1/
bx .
b0 -
b0 ,
b0 +
b0 *
b0 )
b0 (
0'
bx &
0%
bx $
bx #
b0 "
b0 !
$end
#100
b1 "
b0 .
1:
#200
0:
#300
b10 "
b10000000000000000000000000000000 !
1:
#400
0:
#500
b11 "
b1 .
1:
#600
0:
#700
b100 "
b10000000001000000000000000000000 !
1:
#800
0:
#900
b101 "
b10 .
1:
#1000
0:
#1100
b110 "
b10000000001000001100001000000000 !
1:
#1200
0:
#1300
b111 "
b11 .
1:
#1400
0:
#1500
b1000 "
b10000000001000001100001000010011 !
1:
#1600
0:
#1700
b0 .
b1 7
b0 "
1:
#1800
0:
#1900
b1 "
b10 9
1:
#2000
0:
#2100
b10 "
b11111111111111111111000000000000 )
b100 1
b100 *
b1 2
b100000000010 ,
1:
#2200
0:
#2300
b11 "
b11111111111111111111111111110011 5
1:
#2400
0:
#2500
b10 7
b0 "
1:
#2600
0:
#2700
b1 "
b111111110011 (
1:
#2800
0:
#2900
b0 "
b11 7
1:
#3000
0:
#3100
b1 "
1:
#3200
0:
#3300
b10 "
b11111111111111111111111111110011 #
1:
#3400
0:
#3500
b11 "
1:
#3600
0:
#3700
b100 "
1:
#3800
0:
#3900
b0 "
b100 7
1:
#4000
0:
#4100
b1 "
b1 -
b100 0
1:
#4200
0:
#4300
b0 7
b0 "
1:
#4400
0:
#4500
b1 "
1:
#4600
0:
#4700
b10 "
1:
#4800
0:
#4900
b11 "
b1 .
1:
#5000
0:
#5100
b100 "
1:
#5200
0:
#5300
b101 "
b10 .
1:
#5400
0:
#5500
b110 "
1:
#5600
0:
#5700
b111 "
b11 .
1:
#5800
0:
#5900
b1000 "
1:
#6000
0:
#6100
b0 .
b1 7
b0 "
1:
#6200
0:
#6300
b1 "
1:
#6400
0:
#6500
b10 "
1:
#6600
0:
#6700
b11 "
1:
#6800
0:
#6900
b10 7
b0 "
1:
#7000
0:
#7100
b1 "
1:
#7200
0:
#7300
b0 "
b11 7
1:
#7400
0:
#7500
b1 "
1:
#7600
0:
#7700
b10 "
1:
#7800
0:
#7900
b11 "
1:
#8000
0:
#8100
b100 "
1:
#8200
0:
#8300
b0 "
b100 7
1:
#8400
0:
#8500
b1 "
b10 -
b1000 0
1:
#8600
0:
#8700
b0 7
b0 "
1:
#8800
0:
#8900
b1 "
1:
#9000
0:
#9100
b10 "
1:
#9200
0:
#9300
b11 "
b1 .
1:
#9400
0:
#9500
b100 "
1:
#9600
0:
#9700
b101 "
b10 .
1:
#9800
0:
#9900
b110 "
1:
