testing/HoloRiscV.v
/*

This version of the core will use a 32 bit bus for address and 8 bit bus for data, along with separate instruction and data memories. It will implement the RV32I architecture.

NOTE: This version is not meant for implementation. It is the active development version meant to be run in a testbench.

*/

`timescale 1ns/100ps
`default_nettype none

module HoloRiscV (

	);
	
	reg [7:0] instr_mem [0:15];
	reg [7:0] prog_mem [0:15];

	initial begin
		$dumpfile("HoloRiscV.vcd");
		$dumpvars(0,HoloRiscV);
		$readmemb("instr.mem",instr_mem);
		$readmemb("prog.mem",prog_mem);
		#5000 $finish;
	end

	reg clk = 0;

	always #10 clk = !clk;

	//Define stages
	parameter FETCH = 3'b000;
	parameter DECODE = 3'b001;
	parameter EXECUTE = 3'b010;
	parameter MEMORY = 3'b011;
	parameter WRITEBACK = 3'b100;

	//Define ALUI operations
	parameter ADDI = 3'b000;
	parameter SLTI = 3'b010;
	parameter SLTIU = 3'b011;
	parameter XORI = 3'b100;
	parameter ORI = 3'b110;
	parameter ANDI = 3'b111;
	parameter SLLI = 3'b001;
	parameter SRI = 3'b101;
	
	//Define ALU operations
	parameter ADD = 3'b000;
	parameter SLL = 3'b001;
	parameter SLT = 3'b010;
	parameter SLTU = 3'b011;
	parameter XOR = 3'b100;
	parameter SR = 3'b101;
	parameter OR = 3'b110;
	parameter AND = 3'b111;

	//Define branches
	parameter BEQ = 3'b000;
	parameter BNE = 3'b001;
	parameter BLT = 3'b100;
	parameter BGE = 3'b101;
	parameter BLTU = 3'b110;
	parameter BGEU = 3'b111;

	//Define load operations
	parameter LB = 3'b000;
	parameter LH = 3'b001;
	parameter LW = 3'b010;
	parameter LBU = 3'b100;
	parameter LHU = 3'b101;
	
	//Define store operations
	parameter SB = 3'b000;
	parameter SH = 3'b001;
	parameter SW = 3'b010;

	//Define instruction formats
	parameter R = 3'b001;
	parameter I = 3'b010;
	parameter S = 3'b011;
	parameter B = 3'b100;
	parameter U = 3'b101;
	parameter J = 3'b110;

	//Define opcodes
	parameter LUI = 7'b0110111;
	parameter AUIPC = 7'b0010111;
	parameter JAL = 7'b1101111;
	parameter JALR = 7'b1100111;
	parameter BRANCH = 7'b1100011;
	parameter LOAD = 7'b0000011;
	parameter STORE = 7'b0100011;
	parameter ALUI = 7'b0010011;
	parameter ALU = 7'b0110011;

	//Instruction memory I/O
	reg [3:0] INSTR_ADDR;
	reg [7:0] INSTR_DATA;
	reg INSTR_OE = 1;
	
	//Program memory I/O
	reg [31:0] DATA_ADDR;
	reg [7:0] DATA_OUT;
	reg [7:0] DATA_IN;
	reg DATA_OE = 0;
	reg DATA_WE = 0;

	//Registers
	reg [31:0] CMD = 0;
	reg [31:0] REG_FILE [0:31];
	reg [31:0] PC = 0;

	//Control registers
	reg [2:0] STAGE = 0;
	reg [3:0] CYCLE = 4'b0000;
	reg [3:0] SCYCLE = 4'b0000;
	reg [2:0] TYPE;

	//Intermediate registers
	reg [4:0] RD = 0;
	reg [2:0] F3 = 0;
	reg [4:0] RS1 = 0;
	reg [4:0] RS2 = 0;
	reg [6:0] F7 = 0;
	reg [31:0] IMM = 0;
	reg [31:0] TMP = 0;
	reg [31:0] SRC1 = 0;
	reg [31:0] SRC2 = 0;
	reg [31:0] DEST = 0;

	always @(posedge clk) begin
		REG_FILE[0] <= {32{1'b0}};
		//FETCH
		if (STAGE == FETCH) begin
			case (CYCLE)
				0 : begin
					INSTR_ADDR <= PC[3:0];
					CYCLE <= 1;
				end
				1 : begin
					CMD[7:0] <= instr_mem[INSTR_ADDR];
					CYCLE <= 2;
				end
				2 : begin
					INSTR_ADDR <= INSTR_ADDR + 1;
					CYCLE <= 3;
				end
				3 : begin
					CMD[15:8] <= instr_mem[INSTR_ADDR];
					CYCLE <= 4;
				end
				4 : begin
					INSTR_ADDR <= INSTR_ADDR + 1;
					CYCLE <= 5;
				end
				5 : begin
					CMD[23:16] <= instr_mem[INSTR_ADDR];
					CYCLE <= 6;
				end
				6 : begin
					INSTR_ADDR <= INSTR_ADDR + 1;
					CYCLE <= 7;
				end
				7 : begin
					CMD[31:24] <= instr_mem[INSTR_ADDR];
					CYCLE <= 8;
				end
				8 : begin
					CYCLE <= 0;
					STAGE <= DECODE;
					INSTR_ADDR <= PC[3:0];
				end
				default : begin
				end
			endcase
		end
		//DECODE
		if (STAGE == DECODE) begin
			case (CYCLE)
				0 : begin
					case (CMD[6:0])
						LUI : TYPE <= U;
						AUIPC : TYPE <= U;
						JAL : TYPE <= J;
						JALR : TYPE <= I;
						BRANCH : TYPE <= B;
						LOAD : TYPE <= I;
						STORE : TYPE <= S;
						ALUI : begin
							case (CMD[14:12])
								3'b001 : TYPE <= R;
								3'b101 : TYPE <= R;
								default : TYPE <= I;
							endcase
						end
						ALU : TYPE <= R;
						default : begin
						end
					endcase
					CYCLE <= 1;
				end
				1 : begin
					case (TYPE)
						R : begin //R
							F7 <= CMD[31:25];
							RS2 <= CMD[24:20];
							RS1 <= CMD[19:15];
							F3 <= CMD[14:12];
							RD <= CMD[11:7];
						end
						I : begin //I
							IMM[11:0] <= CMD[31:20];
							RS1 <= CMD[19:15];
							F3 <= CMD[14:12];
							RD <= CMD[11:7];
						end
						S : begin //S
							IMM[11:0] <= {CMD[31:25],CMD[11:7]};
							RS2 <= CMD[24:20];
							RS1 <= CMD[19:15];
							F3 <= CMD[14:12];
						end
						B : begin //B
							IMM[11:0] <= {CMD[31],CMD[7],CMD[30:25],CMD[11:8]};
							RS2 <= CMD[24:20];
							RS1 <= CMD[19:15];
							F3 <= CMD[14:12];
						end
						U : begin //U
							IMM[31:12] <= CMD[31:12];
							RD <= CMD[11:7];
						end
						J : begin //J
							IMM[20:1] <= {CMD[31],CMD[19:12],CMD[20],CMD[30:21]};
							RD <= CMD[11:7];
						end
						default : begin
						end
					endcase
					CYCLE <= 2;
				end
				2 : begin
					case (TYPE)
						R : begin
							SRC2 <= REG_FILE[RS2];
							SRC1 <= REG_FILE[RS1];
							//SRC1 <= {1'b1,31'b110000000};
							//SRC2 <= 32'b1110010;
						end
						I : begin
							SRC1 <= REG_FILE[RS1];
							//SRC1 <= {1'b0,7'b1,24'b0};
							//SRC1 <= {22'b111111111,10'b1111100};
						end
						S : begin
							SRC2 <= REG_FILE[RS2];
							SRC1 <= REG_FILE[RS1];
						end
						B : begin
							SRC2 <= REG_FILE[RS2];
							SRC1 <= REG_FILE[RS1];
						end
						default : begin
						end
					endcase
					CYCLE <= 3;
				end
				3 : begin
					CYCLE <= 0;
					STAGE <= EXECUTE;
					//STAGE <= FETCH;
					//PC <= PC + 4;
				end
			endcase
		end
		//EXECUTE
		if (STAGE == EXECUTE) begin
			case (CYCLE)
				0 : begin
					case (CMD[6:0])
						LUI : begin
							DEST <= {IMM[31:12],{12{1'b0}}};
							CYCLE <= 1;
						end
						AUIPC : begin
							DEST <= PC + {IMM[31:12],{12{1'b0}}};
							CYCLE <= 1;
						end
						JAL : begin
							case (SCYCLE)
								0: begin
									PC <= PC + {{12{IMM[20]}},IMM[20:1]};
									SCYCLE <= 1;
								end
								1 : begin
									DEST <= PC + 4;
									CYCLE <= 1;
									SCYCLE <= 0;
								end
								default : begin
								end
							endcase	
						end
						JALR : begin
							case (SCYCLE)
								0 : begin
									PC <= SRC1 + {{20{IMM[11]}},IMM[11:0]};
									SCYCLE <= 1;
								end
								1 : begin
									PC[0] <= 1'b0;
									SCYCLE <= 2;
								end
								2 : begin
									PC <= PC + 4;
									SCYCLE <= 3;
									CYCLE <= 1;
								end
								3 : begin
									//STAGE <= MEMORY;
									SCYCLE <= 0;
									CYCLE <= 1;
								end
								default : begin
								end
							endcase
						end
						BRANCH : begin
							case (F3)
								BEQ : begin
									if (SRC1 == SRC2) begin
										PC <= PC + {{20{IMM[12]}},IMM[12:1]};
									end
								end
								BNE : begin
									if (SRC1 != SRC2) begin
										PC <= PC + {{20{IMM[12]}},IMM[12:1]};
									end
								end
								BLT : begin
									if ($signed(SRC1) < $signed(SRC2)) begin
										PC <= PC + {{20{IMM[12]}},IMM[12:1]};
									end
								end
								BGE : begin
									if ($signed(SRC1) >= $signed(SRC2)) begin
										PC <= PC + {{20{IMM[12]}},IMM[12:1]};
									end
								end
								BLTU : begin
									if (SRC1 < SRC2) begin
										PC <= PC + {{20{IMM[12]}},IMM[12:1]};
									end
								end
								BGEU : begin
									if (SRC1 >= SRC2) begin
										PC <= PC + {{20{IMM[12]}},IMM[12:1]};
									end
								end
								default : begin
								end
							endcase
							CYCLE <= 1;
						end
						ALUI : begin
							case (F3)
								ADDI : begin
									DEST <= SRC1 + {{20{IMM[11]}},IMM[11:0]};
									CYCLE <= 1;
								end
								SLTI : begin
									if ($signed(SRC1) < $signed({{20{IMM[11]}},IMM[11:0]})) begin
										DEST <= 1;
									end
									else begin
										DEST <= 0;
									end
									CYCLE <= 1;
								end
								SLTIU : begin
									if (SRC1 < {{20{IMM[11]}},IMM[11:0]}) begin
										DEST <= 1;
									end
									else begin
										DEST <= 0;
									end
									CYCLE <= 1;
								end
								XORI : begin
									DEST <= SRC1 ^ {{20{IMM[11]}},IMM[11:0]};
									CYCLE <= 1;
								end
								ORI : begin
									DEST <= SRC1 | {{20{IMM[11]}},IMM[11:0]};
									CYCLE <= 1;
								end
								ANDI : begin
									DEST <= SRC1 & {{20{IMM[11]}},IMM[11:0]};
									CYCLE <= 1;
								end
								SLLI : begin
									DEST <= SRC1 << CMD[24:20];
									CYCLE <= 1;
								end
								SRI : begin
									case (CMD[30])
										0 : begin
											DEST <= SRC1 >> CMD[24:20];
										end
										1 : begin
											DEST <= $signed(SRC1) >>> CMD[24:20];
										end
									endcase
									CYCLE <= 1;
								end
							endcase
						end
						ALU : begin
							case (F3)
								ADD : begin
									case (CMD[30])
										0 : begin
											DEST <= SRC1 + SRC2;
										end
										1 : begin
											DEST <= SRC1 - SRC2;
										end
									endcase
									CYCLE <= 1;
								end
								SLL : begin
									DEST <= SRC1 << SRC2[4:0];
									CYCLE <= 1;
								end
								SLT : begin
									if ($signed(SRC1) < $signed(SRC2)) begin
										DEST <= 1;
									end
									else begin
										DEST <= 0;
									end
									CYCLE <= 1;
								end
								SLTU : begin
									if (SRC1 < SRC2) begin
										DEST <= 1;
									end
									else begin
										DEST <= 0;
									end
									CYCLE <= 1;
								end
								XOR : begin
									DEST <= SRC1 ^ SRC2;
									CYCLE <= 1;
								end
								SR : begin
									case (CMD[30])
										0 : begin
											DEST <= SRC1 >> SRC2[4:0];
										end
										1 : begin
											DEST <= $signed(SRC1) >>> SRC2[4:0];
										end
									endcase
									CYCLE <= 1;
								end
								OR : begin
									DEST <= SRC1 | SRC2;
									CYCLE <= 1;
								end
								AND : begin
									DEST <= SRC1 & SRC2;
									CYCLE <= 1;
								end
							endcase
						end
						LOAD : CYCLE <= 1;
						STORE : CYCLE <= 1;
						default : begin
						end
					endcase
				end
				1 : begin
					STAGE <= MEMORY;
					CYCLE <= 0;
					SCYCLE <= 0;
				end
			endcase
		end
		//MEMORY
		if (STAGE == MEMORY) begin
			DATA_IN <= prog_mem[DATA_ADDR];
			case (CYCLE)
				0 : begin
					case (CMD[6:0])
						LOAD : begin
							DATA_WE <= 0;
							DATA_OE <= 1;
						end
						STORE : begin
							DATA_OE <= 0;
							DATA_WE <= 1;
						end
						default : begin
						end
					endcase
					CYCLE <= 1;
				end
				1 : begin
					DATA_ADDR <= SRC1 + {{20{IMM[11]}},IMM[11:0]};
					CYCLE <= 2;
				end
				2 : begin
					case (CMD[6:0])
						LOAD : begin
							case (F3)
								LB : begin
									DEST <= {{24{DATA_IN[7]}},DATA_IN};
									CYCLE <= 3;
								end
								LH : begin
									case (SCYCLE)
										0 : begin
											DEST[7:0] <= DATA_IN;
											SCYCLE <= 1;
										end
										1 : begin
											DATA_ADDR <= DATA_ADDR + 1;
											SCYCLE <= 2;
										end
										2 : begin
											DEST[31:8] <= {{16{DATA_IN[7]}},DATA_IN};
											SCYCLE <= 0;
											CYCLE <= 3;
										end
										default : begin
										end
									endcase
								end
								LW : begin
									case (SCYCLE)
										0 : begin
											DEST[7:0] <= DATA_IN;
											SCYCLE <= 1;
										end
										1 : begin
											DATA_ADDR <= DATA_ADDR + 1;
											SCYCLE <= 2;
										end
										2 : begin
											DEST[15:8] <= DATA_IN;
											SCYCLE <= 3;
										end
										3 : begin
											DATA_ADDR <= DATA_ADDR + 1;
											SCYCLE <= 4;
										end
										4 : begin
											DEST[23:16] <= DATA_IN;
											SCYCLE <= 5;
										end
										5 : begin
											DATA_ADDR <= DATA_ADDR + 1;
											SCYCLE <= 6;
										end
										6 : begin
											DEST[31:24] <= DATA_IN;
											SCYCLE <= 0;
											CYCLE <= 3;
										end
										default : begin
										end
									endcase
								end
								LBU : begin
									DEST <= {{24{1'b0}},DATA_IN};
									CYCLE <= 3;
								end
								LHU : begin
									case (SCYCLE)
										0 : begin
											DEST[7:0] <= DATA_IN;
											SCYCLE <= 1;
										end
										1 : begin
											DATA_ADDR <= DATA_ADDR + 1;
											SCYCLE <= 2;
										end
										2 : begin
											DEST[31:8] <= {{16{1'b0}},DATA_IN};
											CYCLE <= 3;
											SCYCLE <= 0;
										end
										default : begin
										end
									endcase
								end
								default : begin
								end
							endcase
						end
						STORE : begin
							case (F3)
								SB : begin
									DATA_OUT <= SRC2[7:0];
									CYCLE <= 3;
								end
								SH : begin
									case (SCYCLE)
										0 : begin
											DATA_OUT <= SRC2[7:0];
											SCYCLE <= 1;
										end
										1 : begin
											DATA_ADDR <= DATA_ADDR + 1;
											SCYCLE <= 2;
										end
										2 : begin
											DATA_OUT <= SRC2[15:8];
											SCYCLE <= 0;
											CYCLE <= 3;
										end
										default : begin
										end
									endcase
								end
								SW : begin
									case (SCYCLE)
										0 : begin
											DATA_OUT <= SRC2[7:0];
											SCYCLE <= 1;
										end
										1 : begin
											DATA_ADDR <= DATA_ADDR + 1;
											SCYCLE <= 2;
										end
										2 : begin
											DATA_OUT <= SRC2[15:8];
											SCYCLE <= 3;
										end
										3 : begin
											DATA_ADDR <= DATA_ADDR + 1;
											SCYCLE <= 4;
										end
										4 : begin
											DATA_OUT <= SRC2[23:16];
											SCYCLE <= 5;
										end
										5 : begin
											DATA_ADDR <= DATA_ADDR + 1;
											SCYCLE <= 6;
										end
										6 : begin
											DATA_OUT <= SRC2[31:24];
											SCYCLE <= 0;
											CYCLE <= 3;
										end
										default : begin
										end
									endcase
								end
								default : begin
								end
							endcase
						end
						default : begin
							CYCLE <= 3;
						end
					endcase
				end
				3 : begin
					STAGE <= WRITEBACK;
					CYCLE <= 0;
					SCYCLE <= 0;
					DATA_OE <= 0;
					DATA_WE <= 0;
				end
			endcase
		end
		//WRITEBACK
		if (STAGE == WRITEBACK) begin
			case (CYCLE)
				0 : begin
					REG_FILE[RD] <= DEST;
					PC <= PC + 4;
					CYCLE <= 1;
				end
				1 : begin
					CYCLE <= 0;
					STAGE <= FETCH;
				end
				default : begin
				end
			endcase
		end
	end
endmodule

testing/HoloRiscV.vcd
$date
	Thu Mar 18 08:13:02 2021
$end
$version
	Icarus Verilog
$end
$timescale
	100ps
$end
$scope module HoloRiscV $end
$var reg 32 ! CMD [31:0] $end
$var reg 4 " CYCLE [3:0] $end
$var reg 32 # DATA_ADDR [31:0] $end
$var reg 8 $ DATA_IN [7:0] $end
$var reg 1 % DATA_OE $end
$var reg 8 & DATA_OUT [7:0] $end
$var reg 1 ' DATA_WE $end
$var reg 32 ( DEST [31:0] $end
$var reg 3 ) F3 [2:0] $end
$var reg 7 * F7 [6:0] $end
$var reg 32 + IMM [31:0] $end
$var reg 4 , INSTR_ADDR [3:0] $end
$var reg 1 - INSTR_OE $end
$var reg 32 . PC [31:0] $end
$var reg 5 / RD [4:0] $end
$var reg 5 0 RS1 [4:0] $end
$var reg 5 1 RS2 [4:0] $end
$var reg 4 2 SCYCLE [3:0] $end
$var reg 32 3 SRC1 [31:0] $end
$var reg 32 4 SRC2 [31:0] $end
$var reg 3 5 STAGE [2:0] $end
$var reg 32 6 TMP [31:0] $end
$var reg 3 7 TYPE [2:0] $end
$var reg 1 8 clk $end
$upscope $end
$enddefinitions $end
#0
$dumpvars
08
bx 7
b0 6
b0 5
b0 4
b0 3
b0 2
b0 1
b0 0
b0 /
b0 .
1-
bx ,
b0 +
b0 *
b0 )
b0 (
0'
bx &
0%
bx $
bx #
b0 "
b0 !
$end
#100
b1 "
b0 ,
18
#200
08
#300
b10 "
b10011 !
18
#400
08
#500
b11 "
b1 ,
18
#600
08
#700
b100 "
b101000000010011 !
18
#800
08
#900
b101 "
b10 ,
18
#1000
08
#1100
b110 "
b10100110101000000010011 !
18
#1200
08
#1300
b111 "
b11 ,
18
#1400
08
#1500
b1000 "
b1000000010100110101000000010011 !
18
#1600
08
#1700
b0 ,
b1 5
b0 "
18
#1800
08
#1900
b1 "
b1 7
18
#2000
08
#2100
b10 "
b101 )
b110 0
b101 1
b100000 *
18
#2200
08
#2300
b11 "
bx 3
bx 4
18
#2400
08
#2500
b10 5
b0 "
18
#2600
08
#2700
b1 "
bx (
18
#2800
08
#2900
b0 "
b11 5
18
#3000
08
#3100
b1 "
18
#3200
08
#3300
b10 "
18
#3400
08
#3500
b11 "
18
#3600
08
#3700
b0 "
b100 5
18
#3800
08
#3900
b1 "
b100 .
18
#4000
08
#4100
b0 5
b0 "
18
#4200
08
#4300
b1 "
b100 ,
18
#4400
08
#4500
b10 "
b1000000010100110101000000010111 !
18
#4600
08
#4700
b11 "
b101 ,
18
#4800
08
#4900
b100 "
b1000000010100110000000000010111 !
18
#5000
08
#5100
b101 "
b110 ,
18
#5200
08
#5300
b110 "
b1000000000000000000000000010111 !
18
#5400
08
#5500
b111 "
b111 ,
18
#5600
08
#5700
b1000 "
b11111111000000000000000000010111 !
18
#5800
08
#5900
b100 ,
b1 5
b0 "
18
#6000
08
#6100
b1 "
b101 7
18
#6200
08
#6300
b10 "
b11111111000000000000000000000000 +
18
#6400
08
#6500
b11 "
18
#6600
08
#6700
b10 5
b0 "
18
#6800
08
#6900
b1 "
b11111111000000000000000000000100 (
18
#7000
08
#7100
b0 "
b11 5
18
#7200
08
#7300
b1 "
18
#7400
08
#7500
b10 "
18
#7600
08
#7700
b11 "
18
#7800
08
#7900
b0 "
b100 5
18
#8000
08
#8100
b1 "
b1000 .
18
#8200
08
#8300
b0 5
b0 "
18
#8400
08
#8500
b1 "
b1000 ,
18
#8600
08
#8700
b10 "
b11111111000000000000000001101111 !
18
#8800
08
#8900
b11 "
b1001 ,
18
#9000
08
#9100
b100 "
b11111111000000001111111101101111 !
18
#9200
08
#9300
b101 "
b1010 ,
18
#9400
08
#9500
b110 "
18
#9600
08
#9700
b111 "
b1011 ,
18
#9800
08
#9900
b1000 "
b1111111101101111 !
18
#10000
08
#10100
b1000 ,
b1 5
b0 "
18
#10200
08
#10300
b1 "
b110 7
18
#10400
08
#10500
b10 "
b11110 /
b11111111000000001111000000000000 +
18
#10600
08
#10700
b11 "
18
#10800
08
#10900
b10 5
b0 "
18
#11000
08
#11100
b1 2
b111100000001000 .
18
#11200
08
#11300
b0 2
b1 "
b111100000001100 (
18
#11400
08
#11500
b0 "
b11 5
18
#11600
08
#11700
b1 "
18
#11800
08
#11900
b10 "
18
#12000
08
#12100
b11 "
18
#12200
08
#12300
b0 "
b100 5
18
#12400
08
#12500
b1 "
b111100000001100 .
18
#12600
08
#12700
b0 5
b0 "
18
#12800
08
#12900
b1 "
b1100 ,
18
#13000
08
#13100
b10 "
b1111111100110011 !
18
#13200
08
#13300
b11 "
b1101 ,
18
#13400
08
#13500
b100 "
b110011 !
18
#13600
08
#13700
b101 "
b1110 ,
18
#13800
08
#13900
b110 "
b111111110000000000110011 !
18
#14000
08
#14100
b111 "
b1111 ,
18
#14200
08
#14300
b1000 "
18
#14400
08
#14500
b1100 ,
b1 5
b0 "
18
#14600
08
#14700
b1 "
b1 7
18
#14800
08
#14900
b10 "
b0 /
b0 )
b11110 0
b1111 1
b0 *
18
#15000
08
#15100
b11 "
b111100000001100 3
18
#15200
08
#15300
b10 5
b0 "
18
#15400
08
#15500
b1 "
bx (
18
#15600
08
#15700
b0 "
b11 5
18
#15800
08
#15900
b1 "
18
#16000
08
#16100
b10 "
b111100000001100 #
18
#16200
08
#16300
b11 "
18
#16400
08
#16500
b0 "
b100 5
18
#16600
08
#16700
b1 "
b111100000010000 .
18
#16800
08
#16900
b0 5
b0 "
18
#17000
08
#17100
b1 "
b0 ,
18
#17200
08
#17300
b10 "
b111111110000000000010011 !
18
#17400
08
#17500
b11 "
b1 ,
18
#17600
08
#17700
b100 "
b111111110101000000010011 !
18
#17800
08
#17900
b101 "
b10 ,
18
#18000
08
#18100
b110 "
b10100110101000000010011 !
18
#18200
08
#18300
b111 "
b11 ,
18
#18400
08
#18500
b1000 "
b1000000010100110101000000010011 !
18
#18600
08
#18700
b0 ,
b1 5
b0 "
18
#18800
08
#18900
b1 "
18
#19000
08
#19100
b10 "
b101 )
b110 0
b101 1
b100000 *
18
#19200
08
#19300
b11 "
bx 3
18
#19400
08
#19500
b10 5
b0 "
18
#19600
08
#19700
b1 "
18
#19800
08
#19900
b0 "
b11 5
18
#20000
08
#20100
b1 "
18
#20200
08
#20300
b10 "
bx #
18
#20400
08
#20500
b11 "
18
#20600
08
#20700
b0 "
b100 5
18
#20800
08
#20900
b1 "
b111100000010100 .
18
#21000
08
#21100
b0 5
b0 "
18
#21200
08
#21300
b1 "
b100 ,
18
#21400
08
#21500
b10 "
b1000000010100110101000000010111 !
18
#21600
08
#21700
b11 "
b101 ,
18
#21800
08
#21900
b100 "
b1000000010100110000000000010111 !
18
#22000
08
#22100
b101 "
b110 ,
18
#22200
08
#22300
b110 "
b1000000000000000000000000010111 !
18
#22400
08
#22500
b111 "
b111 ,
18
#22600
08
#22700
b1000 "
b11111111000000000000000000010111 !
18
#22800
08
#22900
b100 ,
b1 5
b0 "
18
#23000
08
#23100
b1 "
b101 7
18
#23200
08
#23300
b10 "
b11111111000000000000000000000000 +
18
#23400
08
#23500
b11 "
18
#23600
08
#23700
b10 5
b0 "
18
#23800
08
#23900
b1 "
b11111111000000000111100000010100 (
18
#24000
08
#24100
b0 "
b11 5
18
#24200
08
#24300
b1 "
18
#24400
08
#24500
b10 "
18
#24600
08
#24700
b11 "
18
#24800
08
#24900
b0 "
b100 5
18
#25000
08
#25100
b1 "
b111100000011000 .
18
#25200
08
#25300
b0 5
b0 "
18
#25400
08
#25500
b1 "
b1000 ,
18
#25600
08
#25700
b10 "
b11111111000000000000000001101111 !
18
#25800
08
#25900
b11 "
b1001 ,
18
#26000
08
#26100
b100 "
b11111111000000001111111101101111 !
18
#26200
08
#26300
b101 "
b1010 ,
18
#26400
08
#26500
b110 "
18
#26600
08
#26700
b111 "
b1011 ,
18
#26800
08
#26900
b1000 "
b1111111101101111 !
18
#27000
08
#27100
b1000 ,
b1 5
b0 "
18
#27200
08
#27300
b1 "
b110 7
18
#27400
08
#27500
b10 "
b11110 /
b11111111000000001111000000000000 +
18
#27600
08
#27700
b11 "
18
#27800
08
#27900
b10 5
b0 "
18
#28000
08
#28100
b1 2
b1111000000011000 .
18
#28200
08
#28300
b0 2
b1 "
b1111000000011100 (
18
#28400
08
#28500
b0 "
b11 5
18
#28600
08
#28700
b1 "
18
#28800
08
#28900
b10 "
18
#29000
08
#29100
b11 "
18
#29200
08
#29300
b0 "
b100 5
18
#29400
08
#29500
b1 "
b1111000000011100 .
18
#29600
08
#29700
b0 5
b0 "
18
#29800
08
#29900
b1 "
b1100 ,
18
#30000
08
#30100
b10 "
b1111111100110011 !
18
#30200
08
#30300
b11 "
b1101 ,
18
#30400
08
#30500
b100 "
b110011 !
18
#30600
08
#30700
b101 "
b1110 ,
18
#30800
08
#30900
b110 "
b111111110000000000110011 !
18
#31000
08
#31100
b111 "
b1111 ,
18
#31200
08
#31300
b1000 "
18
#31400
08
#31500
b1100 ,
b1 5
b0 "
18
#31600
08
#31700
b1 "
b1 7
18
#31800
08
#31900
b10 "
b0 /
b0 )
b11110 0
b1111 1
b0 *
18
#32000
08
#32100
b11 "
b1111000000011100 3
18
#32200
08
#32300
b10 5
b0 "
18
#32400
08
#32500
b1 "
bx (
18
#32600
08
#32700
b0 "
b11 5
18
#32800
08
#32900
b1 "
18
#33000
08
#33100
b10 "
b1111000000011100 #
18
#33200
08
#33300
b11 "
18
#33400
08
#33500
b0 "
b100 5
18
#33600
08
#33700
b1 "
b1111000000100000 .
18
#33800
08
#33900
b0 5
b0 "
18
#34000
08
#34100
b1 "
b0 ,
18
#34200
08
#34300
b10 "
b111111110000000000010011 !
18
#34400
08
#34500
b11 "
b1 ,
18
#34600
08
#34700
b100 "
b111111110101000000010011 !
18
#34800
08
#34900
b101 "
b10 ,
18
#35000
08
#35100
b110 "
b10100110101000000010011 !
18
#35200
08
#35300
b111 "
b11 ,
18
#35400
08
#35500
b1000 "
b1000000010100110101000000010011 !
18
#35600
08
#35700
b0 ,
b1 5
b0 "
18
#35800
08
#35900
b1 "
18
#36000
08
#36100
b10 "
b101 )
b110 0
b101 1
b100000 *
18
#36200
08
#36300
b11 "
bx 3
18
#36400
08
#36500
b10 5
b0 "
18
#36600
08
#36700
b1 "
18
#36800
08
#36900
b0 "
b11 5
18
#37000
08
#37100
b1 "
18
#37200
08
#37300
b10 "
bx #
18
#37400
08
#37500
b11 "
18
#37600
08
#37700
b0 "
b100 5
18
#37800
08
#37900
b1 "
b1111000000100100 .
18
#38000
08
#38100
b0 5
b0 "
18
#38200
08
#38300
b1 "
b100 ,
18
#38400
08
#38500
b10 "
b1000000010100110101000000010111 !
18
#38600
08
#38700
b11 "
b101 ,
18
#38800
08
#38900
b100 "
b1000000010100110000000000010111 !
18
#39000
08
#39100
b101 "
b110 ,
18
#39200
08
#39300
b110 "
b1000000000000000000000000010111 !
18
#39400
08
#39500
b111 "
b111 ,
18
#39600
08
#39700
b1000 "
b11111111000000000000000000010111 !
18
#39800
08
#39900
b100 ,
b1 5
b0 "
18
#40000
08
#40100
b1 "
b101 7
18
#40200
08
#40300
b10 "
b11111111000000000000000000000000 +
18
#40400
08
#40500
b11 "
18
#40600
08
#40700
b10 5
b0 "
18
#40800
08
#40900
b1 "
b11111111000000001111000000100100 (
18
#41000
08
#41100
b0 "
b11 5
18
#41200
08
#41300
b1 "
18
#41400
08
#41500
b10 "
18
#41600
08
#41700
b11 "
18
#41800
08
#41900
b0 "
b100 5
18
#42000
08
#42100
b1 "
b1111000000101000 .
18
#42200
08
#42300
b0 5
b0 "
18
#42400
08
#42500
b1 "
b1000 ,
18
#42600
08
#42700
b10 "
b11111111000000000000000001101111 !
18
#42800
08
#42900
b11 "
b1001 ,
18
#43000
08
#43100
b100 "
b11111111000000001111111101101111 !
18
#43200
08
#43300
b101 "
b1010 ,
18
#43400
08
#43500
b110 "
18
#43600
08
#43700
b111 "
b1011 ,
18
#43800
08
#43900
b1000 "
b1111111101101111 !
18
#44000
08
#44100
b1000 ,
b1 5
b0 "
18
#44200
08
#44300
b1 "
b110 7
18
#44400
08
#44500
b10 "
b11110 /
b11111111000000001111000000000000 +
18
#44600
08
#44700
b11 "
18
#44800
08
#44900
b10 5
b0 "
18
#45000
08
#45100
b1 2
b10110100000101000 .
18
#45200
08
#45300
b0 2
b1 "
b10110100000101100 (
18
#45400
08
#45500
b0 "
b11 5
18
#45600
08
#45700
b1 "
18
#45800
08
#45900
b10 "
18
#46000
08
#46100
b11 "
18
#46200
08
#46300
b0 "
b100 5
18
#46400
08
#46500
b1 "
b10110100000101100 .
18
#46600
08
#46700
b0 5
b0 "
18
#46800
08
#46900
b1 "
b1100 ,
18
#47000
08
#47100
b10 "
b1111111100110011 !
18
#47200
08
#47300
b11 "
b1101 ,
18
#47400
08
#47500
b100 "
b110011 !
18
#47600
08
#47700
b101 "
b1110 ,
18
#47800
08
#47900
b110 "
b111111110000000000110011 !
18
#48000
08
#48100
b111 "
b1111 ,
18
#48200
08
#48300
b1000 "
18
#48400
08
#48500
b1100 ,
b1 5
b0 "
18
#48600
08
#48700
b1 "
b1 7
18
#48800
08
#48900
b10 "
b0 /
b0 )
b11110 0
b1111 1
b0 *
18
#49000
08
#49100
b11 "
b10110100000101100 3
18
#49200
08
#49300
b10 5
b0 "
18
#49400
08
#49500
b1 "
bx (
18
#49600
08
#49700
b0 "
b11 5
18
#49800
08
#49900
b1 "
18
