testing/HoloRiscV.v
/*

This version of the core will use a 32 bit bus for address and 8 bit bus for data, along with separate instruction and data memories. It will implement the RV32I architecture.

NOTE: This version is not meant for implementation. It is the active development version meant to be run in a testbench.

*/

`timescale 1ns/100ps
`default_nettype none

module HoloRiscV (

	);
	
	reg [7:0] instr_mem [0:15];
	//reg [7:0] prog_mem [0:15];

	initial begin
		$dumpfile("HoloRiscV.vcd");
		$dumpvars(0,HoloRiscV);
		$readmemb("instr.mem",instr_mem);
		//$readmemb("prog.mem",prog_mem);
		#5000 $finish;
	end

	reg clk = 0;

	always #10 clk = !clk;

	//Define stages
	parameter FETCH = 3'b000;
	parameter DECODE = 3'b001;
	parameter EXECUTE = 3'b010;
	parameter MEMORY = 3'b011;
	parameter WRITEBACK = 3'b100;

	//Define instruction formats
	parameter R = 3'b001;
	parameter I = 3'b010;
	parameter S = 3'b011;
	parameter B = 3'b100;
	parameter U = 3'b101;
	parameter J = 3'b110;

	//Define opcodes
	parameter LUI = 7'b0110111;
	parameter AUIPC = 7'b0010111;
	parameter JAL = 7'b1101111;
	parameter JALR = 7'b1100111;
	parameter BRANCH = 7'b1100011;
	parameter LOAD = 7'b0000011;
	parameter STORE = 7'b0100011;
	parameter ALUI = 7'b0010011;
	parameter ALU = 7'b0110011;

	//Instruction memory I/O
	reg [3:0] INSTR_ADDR;
	reg [7:0] INSTR_DATA;
	reg INSTR_OE = 1;
	
	//Registers
	reg [31:0] CMD = 0;
	reg [31:0] REG_FILE [0:31];
	reg [3:0] PC = 0;

	//Control registers
	reg [2:0] STAGE = 0;
	reg [3:0] CYCLE = 4'b0000;
	reg [3:0] SCYCLE = 4'b0000;
	reg [2:0] TYPE;

	//Intermediate registers
	reg [4:0] RD = 0;
	reg [2:0] F3 = 0;
	reg [4:0] RS1 = 0;
	reg [4:0] RS2 = 0;
	reg [6:0] F7 = 0;
	reg [31:0] IMM = 0;
	reg [31:0] TMP = 0;
	reg [31:0] SRC1 = 0;
	reg [31:0] SRC2 = 0;
	reg [31:0] DEST = 0;

	always @(posedge clk) begin
		REG_FILE[0] <= 32'b0;
		//FETCH
		if (STAGE == FETCH) begin
			case (CYCLE)
				0 : begin
					INSTR_ADDR <= PC;
					CYCLE <= 1;
				end
				1 : begin
					CMD[7:0] <= instr_mem[INSTR_ADDR];
					CYCLE <= 2;
				end
				2 : begin
					INSTR_ADDR <= INSTR_ADDR + 1;
					CYCLE <= 3;
				end
				3 : begin
					CMD[15:8] <= instr_mem[INSTR_ADDR];
					CYCLE <= 4;
				end
				4 : begin
					INSTR_ADDR <= INSTR_ADDR + 1;
					CYCLE <= 5;
				end
				5 : begin
					CMD[23:16] <= instr_mem[INSTR_ADDR];
					CYCLE <= 6;
				end
				6 : begin
					INSTR_ADDR <= INSTR_ADDR + 1;
					CYCLE <= 7;
				end
				7 : begin
					CMD[31:24] <= instr_mem[INSTR_ADDR];
					CYCLE <= 8;
				end
				8 : begin
					CYCLE <= 0;
					STAGE <= DECODE;
					INSTR_ADDR <= PC;
				end
				default : begin
				end
			endcase
		end
		//DECODE
		if (STAGE == DECODE) begin
			case (CYCLE)
				0 : begin
					case (CMD[6:0])
						LUI : TYPE <= U;
						AUIPC : TYPE <= U;
						JAL : TYPE <= J;
						JALR : TYPE <= I;
						BRANCH : TYPE <= B;
						LOAD : TYPE <= I;
						STORE : TYPE <= S;
						ALUI : begin
							case (CMD[14:12])
								3'b001 : TYPE <= R;
								3'b101 : TYPE <= R;
								default : TYPE <= I;
							endcase
						end
						ALU : TYPE <= R;
						default : begin
						end
					endcase
					CYCLE <= 1;
				end
				1 : begin
					case (TYPE)
						R : begin //R
							F7 <= CMD[31:25];
							RS2 <= CMD[24:20];
							RS1 <= CMD[19:15];
							F3 <= CMD[14:12];
							RD <= CMD[11:7];
						end
						I : begin //I
							IMM[11:0] <= CMD[31:20];
							RS1 <= CMD[19:15];
							F3 <= CMD[14:12];
							RD <= CMD[11:7];
						end
						S : begin //S
							IMM[11:0] <= {CMD[31:25],CMD[11:7]};
							RS2 <= CMD[24:20];
							RS1 <= CMD[19:15];
							F3 <= CMD[14:12];
						end
						B : begin //B
							IMM[11:0] <= {CMD[31],CMD[7],CMD[30:25],CMD[11:8]};
							RS2 <= CMD[24:20];
							RS1 <= CMD[19:15];
							F3 <= CMD[14:12];
						end
						U : begin //U
							IMM[31:12] <= CMD[31:12];
							RD <= CMD[11:7];
						end
						J : begin //J
							IMM[20:1] <= {CMD[31],CMD[19:12],CMD[20],CMD[30:21]};
							RD <= CMD[11:7];
						end
						default : begin
						end
					endcase
					CYCLE <= 2;
				end
				2 : begin
					case (TYPE)
						R : begin
							SRC2 <= REG_FILE[RS2];
							SRC1 <= REG_FILE[RS1];
						end
						I : begin
							SRC1 <= REG_FILE[RS1];
						end
						S : begin
							SRC2 <= REG_FILE[RS2];
							SRC1 <= REG_FILE[RS1];
						end
						B : begin
							SRC2 <= REG_FILE[RS2];
							SRC1 <= REG_FILE[RS1];
						end
						default : begin
						end
					endcase
					CYCLE <= 3;
				end
				3 : begin
					CYCLE <= 0;
					STAGE <= EXECUTE;
					//STAGE <= FETCH;
					//PC <= PC + 4;
				end
			endcase
		end
		//EXECUTE
		if (STAGE == EXECUTE) begin
			
		end
	end
endmodule

testing/HoloRiscV.vcd
$date
	Wed Mar 17 10:50:47 2021
$end
$version
	Icarus Verilog
$end
$timescale
	100ps
$end
$scope module HoloRiscV $end
$var reg 32 ! CMD [31:0] $end
$var reg 4 " CYCLE [3:0] $end
$var reg 32 # DEST [31:0] $end
$var reg 3 $ F3 [2:0] $end
$var reg 7 % F7 [6:0] $end
$var reg 32 & IMM [31:0] $end
$var reg 4 ' INSTR_ADDR [3:0] $end
$var reg 1 ( INSTR_OE $end
$var reg 4 ) PC [3:0] $end
$var reg 5 * RD [4:0] $end
$var reg 5 + RS1 [4:0] $end
$var reg 5 , RS2 [4:0] $end
$var reg 4 - SCYCLE [3:0] $end
$var reg 32 . SRC1 [31:0] $end
$var reg 32 / SRC2 [31:0] $end
$var reg 3 0 STAGE [2:0] $end
$var reg 32 1 TMP [31:0] $end
$var reg 3 2 TYPE [2:0] $end
$var reg 1 3 clk $end
$upscope $end
$enddefinitions $end
#0
$dumpvars
03
bx 2
b0 1
b0 0
b0 /
b0 .
b0 -
b0 ,
b0 +
b0 *
b0 )
1(
bx '
b0 &
b0 %
b0 $
b0 #
b0 "
b0 !
$end
#100
b1 "
b0 '
13
#200
03
#300
b10 "
b110111 !
13
#400
03
#500
b11 "
b1 '
13
#600
03
#700
b100 "
13
#800
03
#900
b101 "
b10 '
13
#1000
03
#1100
b110 "
b111111110000000000110111 !
13
#1200
03
#1300
b111 "
b11 '
13
#1400
03
#1500
b1000 "
13
#1600
03
#1700
b0 '
b1 0
b0 "
13
#1800
03
#1900
b1 "
b101 2
13
#2000
03
#2100
b10 "
b111111110000000000000000 &
13
#2200
03
#2300
b11 "
13
#2400
03
#2500
b100 )
b0 0
b0 "
13
#2600
03
#2700
b1 "
b100 '
13
#2800
03
#2900
b10 "
b111111110000000000010111 !
13
#3000
03
#3100
b11 "
b101 '
13
#3200
03
#3300
b100 "
13
#3400
03
#3500
b101 "
b110 '
13
#3600
03
#3700
b110 "
b10111 !
13
#3800
03
#3900
b111 "
b111 '
13
#4000
03
#4100
b1000 "
b11111111000000000000000000010111 !
13
#4200
03
#4300
b100 '
b1 0
b0 "
13
#4400
03
#4500
b1 "
13
#4600
03
#4700
b10 "
b11111111000000000000000000000000 &
13
#4800
03
#4900
b11 "
13
#5000
03
#5100
b1000 )
b0 0
b0 "
13
#5200
03
#5300
b1 "
b1000 '
13
#5400
03
#5500
b10 "
b11111111000000000000000001101111 !
13
#5600
03
#5700
b11 "
b1001 '
13
#5800
03
#5900
b100 "
b11111111000000001111111101101111 !
13
#6000
03
#6100
b101 "
b1010 '
13
#6200
03
#6300
b110 "
13
#6400
03
#6500
b111 "
b1011 '
13
#6600
03
#6700
b1000 "
b1111111101101111 !
13
#6800
03
#6900
b1000 '
b1 0
b0 "
13
#7000
03
#7100
b1 "
b110 2
13
#7200
03
#7300
b10 "
b11110 *
b11111111000000001111000000000000 &
13
#7400
03
#7500
b11 "
13
#7600
03
#7700
b1100 )
b0 0
b0 "
13
#7800
03
#7900
b1 "
b1100 '
13
#8000
03
#8100
b10 "
b1111111100110011 !
13
#8200
03
#8300
b11 "
b1101 '
13
#8400
03
#8500
b100 "
b110011 !
13
#8600
03
#8700
b101 "
b1110 '
13
#8800
03
#8900
b110 "
b111111110000000000110011 !
13
#9000
03
#9100
b111 "
b1111 '
13
#9200
03
#9300
b1000 "
13
#9400
03
#9500
b1100 '
b1 0
b0 "
13
#9600
03
#9700
b1 "
b1 2
13
#9800
03
#9900
b10 "
b0 *
b11110 +
b1111 ,
13
#10000
03
#10100
b11 "
bx .
bx /
13
#10200
03
#10300
b0 )
b0 0
b0 "
13
#10400
03
#10500
b1 "
b0 '
13
#10600
03
#10700
b10 "
b111111110000000000110111 !
13
#10800
03
#10900
b11 "
b1 '
13
#11000
03
#11100
b100 "
13
#11200
03
#11300
b101 "
b10 '
13
#11400
03
#11500
b110 "
13
#11600
03
#11700
b111 "
b11 '
13
#11800
03
#11900
b1000 "
13
#12000
03
#12100
b0 '
b1 0
b0 "
13
#12200
03
#12300
b1 "
b101 2
13
#12400
03
#12500
b10 "
b111111110000000000000000 &
13
#12600
03
#12700
b11 "
13
#12800
03
#12900
b100 )
b0 0
b0 "
13
#13000
03
#13100
b1 "
b100 '
13
#13200
03
#13300
b10 "
b111111110000000000010111 !
13
#13400
03
#13500
b11 "
b101 '
13
#13600
03
#13700
b100 "
13
#13800
03
#13900
b101 "
b110 '
13
#14000
03
#14100
b110 "
b10111 !
13
#14200
03
#14300
b111 "
b111 '
13
#14400
03
#14500
b1000 "
b11111111000000000000000000010111 !
13
#14600
03
#14700
b100 '
b1 0
b0 "
13
#14800
03
#14900
b1 "
13
#15000
03
#15100
b10 "
b11111111000000000000000000000000 &
13
#15200
03
#15300
b11 "
13
#15400
03
#15500
b1000 )
b0 0
b0 "
13
#15600
03
#15700
b1 "
b1000 '
13
#15800
03
#15900
b10 "
b11111111000000000000000001101111 !
13
#16000
03
#16100
b11 "
b1001 '
13
#16200
03
#16300
b100 "
b11111111000000001111111101101111 !
13
#16400
03
#16500
b101 "
b1010 '
13
#16600
03
#16700
b110 "
13
#16800
03
#16900
b111 "
b1011 '
13
#17000
03
#17100
b1000 "
b1111111101101111 !
13
#17200
03
#17300
b1000 '
b1 0
b0 "
13
#17400
03
#17500
b1 "
b110 2
13
#17600
03
#17700
b10 "
b11110 *
b11111111000000001111000000000000 &
13
#17800
03
#17900
b11 "
13
#18000
03
#18100
b1100 )
b0 0
b0 "
13
#18200
03
#18300
b1 "
b1100 '
13
#18400
03
#18500
b10 "
b1111111100110011 !
13
#18600
03
#18700
b11 "
b1101 '
13
#18800
03
#18900
b100 "
b110011 !
13
#19000
03
#19100
b101 "
b1110 '
13
#19200
03
#19300
b110 "
b111111110000000000110011 !
13
#19400
03
#19500
b111 "
b1111 '
13
#19600
03
#19700
b1000 "
13
#19800
03
#19900
b1100 '
b1 0
b0 "
13
#20000
03
#20100
b1 "
b1 2
13
#20200
03
#20300
b10 "
b0 *
13
#20400
03
#20500
b11 "
13
#20600
03
#20700
b0 )
b0 0
b0 "
13
#20800
03
#20900
b1 "
b0 '
13
#21000
03
#21100
b10 "
b111111110000000000110111 !
13
#21200
03
#21300
b11 "
b1 '
13
#21400
03
#21500
b100 "
13
#21600
03
#21700
b101 "
b10 '
13
#21800
03
#21900
b110 "
13
#22000
03
#22100
b111 "
b11 '
13
#22200
03
#22300
b1000 "
13
#22400
03
#22500
b0 '
b1 0
b0 "
13
#22600
03
#22700
b1 "
b101 2
13
#22800
03
#22900
b10 "
b111111110000000000000000 &
13
#23000
03
#23100
b11 "
13
#23200
03
#23300
b100 )
b0 0
b0 "
13
#23400
03
#23500
b1 "
b100 '
13
#23600
03
#23700
b10 "
b111111110000000000010111 !
13
#23800
03
#23900
b11 "
b101 '
13
#24000
03
#24100
b100 "
13
#24200
03
#24300
b101 "
b110 '
13
#24400
03
#24500
b110 "
b10111 !
13
#24600
03
#24700
b111 "
b111 '
13
#24800
03
#24900
b1000 "
b11111111000000000000000000010111 !
13
#25000
03
#25100
b100 '
b1 0
b0 "
13
#25200
03
#25300
b1 "
13
#25400
03
#25500
b10 "
b11111111000000000000000000000000 &
13
#25600
03
#25700
b11 "
13
#25800
03
#25900
b1000 )
b0 0
b0 "
13
#26000
03
#26100
b1 "
b1000 '
13
#26200
03
#26300
b10 "
b11111111000000000000000001101111 !
13
#26400
03
#26500
b11 "
b1001 '
13
#26600
03
#26700
b100 "
b11111111000000001111111101101111 !
13
#26800
03
#26900
b101 "
b1010 '
13
#27000
03
#27100
b110 "
13
#27200
03
#27300
b111 "
b1011 '
13
#27400
03
#27500
b1000 "
b1111111101101111 !
13
#27600
03
#27700
b1000 '
b1 0
b0 "
13
#27800
03
#27900
b1 "
b110 2
13
#28000
03
#28100
b10 "
b11110 *
b11111111000000001111000000000000 &
13
#28200
03
#28300
b11 "
13
#28400
03
#28500
b1100 )
b0 0
b0 "
13
#28600
03
#28700
b1 "
b1100 '
13
#28800
03
#28900
b10 "
b1111111100110011 !
13
#29000
03
#29100
b11 "
b1101 '
13
#29200
03
#29300
b100 "
b110011 !
13
#29400
03
#29500
b101 "
b1110 '
13
#29600
03
#29700
b110 "
b111111110000000000110011 !
13
#29800
03
#29900
b111 "
b1111 '
13
#30000
03
#30100
b1000 "
13
#30200
03
#30300
b1100 '
b1 0
b0 "
13
#30400
03
#30500
b1 "
b1 2
13
#30600
03
#30700
b10 "
b0 *
13
#30800
03
#30900
b11 "
13
#31000
03
#31100
b0 )
b0 0
b0 "
13
#31200
03
#31300
b1 "
b0 '
13
#31400
03
#31500
b10 "
b111111110000000000110111 !
13
#31600
03
#31700
b11 "
b1 '
13
#31800
03
#31900
b100 "
13
#32000
03
#32100
b101 "
b10 '
13
#32200
03
#32300
b110 "
13
#32400
03
#32500
b111 "
b11 '
13
#32600
03
#32700
b1000 "
13
#32800
03
#32900
b0 '
b1 0
b0 "
13
#33000
03
#33100
b1 "
b101 2
13
#33200
03
#33300
b10 "
b111111110000000000000000 &
13
#33400
03
#33500
b11 "
13
#33600
03
#33700
b100 )
b0 0
b0 "
13
#33800
03
#33900
b1 "
b100 '
13
#34000
03
#34100
b10 "
b111111110000000000010111 !
13
#34200
03
#34300
b11 "
b101 '
13
#34400
03
#34500
b100 "
13
#34600
03
#34700
b101 "
b110 '
13
#34800
03
#34900
b110 "
b10111 !
13
#35000
03
#35100
b111 "
b111 '
13
#35200
03
#35300
b1000 "
b11111111000000000000000000010111 !
13
#35400
03
#35500
b100 '
b1 0
b0 "
13
#35600
03
#35700
b1 "
13
#35800
03
#35900
b10 "
b11111111000000000000000000000000 &
13
#36000
03
#36100
b11 "
13
#36200
03
#36300
b1000 )
b0 0
b0 "
13
#36400
03
#36500
b1 "
b1000 '
13
#36600
03
#36700
b10 "
b11111111000000000000000001101111 !
13
#36800
03
#36900
b11 "
b1001 '
13
#37000
03
#37100
b100 "
b11111111000000001111111101101111 !
13
#37200
03
#37300
b101 "
b1010 '
13
#37400
03
#37500
b110 "
13
#37600
03
#37700
b111 "
b1011 '
13
#37800
03
#37900
b1000 "
b1111111101101111 !
13
#38000
03
#38100
b1000 '
b1 0
b0 "
13
#38200
03
#38300
b1 "
b110 2
13
#38400
03
#38500
b10 "
b11110 *
b11111111000000001111000000000000 &
13
#38600
03
#38700
b11 "
13
#38800
03
#38900
b1100 )
b0 0
b0 "
13
#39000
03
#39100
b1 "
b1100 '
13
#39200
03
#39300
b10 "
b1111111100110011 !
13
#39400
03
#39500
b11 "
b1101 '
13
#39600
03
#39700
b100 "
b110011 !
13
#39800
03
#39900
b101 "
b1110 '
13
#40000
03
#40100
b110 "
b111111110000000000110011 !
13
#40200
03
#40300
b111 "
b1111 '
13
#40400
03
#40500
b1000 "
13
#40600
03
#40700
b1100 '
b1 0
b0 "
13
#40800
03
#40900
b1 "
b1 2
13
#41000
03
#41100
b10 "
b0 *
13
#41200
03
#41300
b11 "
13
#41400
03
#41500
b0 )
b0 0
b0 "
13
#41600
03
#41700
b1 "
b0 '
13
#41800
03
#41900
b10 "
b111111110000000000110111 !
13
#42000
03
#42100
b11 "
b1 '
13
#42200
03
#42300
b100 "
13
#42400
03
#42500
b101 "
b10 '
13
#42600
03
#42700
b110 "
13
#42800
03
#42900
b111 "
b11 '
13
#43000
03
#43100
b1000 "
13
#43200
03
#43300
b0 '
b1 0
b0 "
13
#43400
03
#43500
b1 "
b101 2
13
#43600
03
#43700
b10 "
b111111110000000000000000 &
13
#43800
03
#43900
b11 "
13
#44000
03
#44100
b100 )
b0 0
b0 "
13
#44200
03
#44300
b1 "
b100 '
13
#44400
03
#44500
b10 "
b111111110000000000010111 !
13
#44600
03
#44700
b11 "
b101 '
13
#44800
03
#44900
b100 "
13
#45000
03
#45100
b101 "
b110 '
13
#45200
03
#45300
b110 "
b10111 !
13
#45400
03
#45500
b111 "
b111 '
13
#45600
03
#45700
b1000 "
b11111111000000000000000000010111 !
13
#45800
03
#45900
b100 '
b1 0
b0 "
13
#46000
03
#46100
b1 "
13
#46200
03
#46300
b10 "
b11111111000000000000000000000000 &
13
#46400
03
#46500
b11 "
13
#46600
03
#46700
b1000 )
b0 0
b0 "
13
#46800
03
#46900
b1 "
b1000 '
13
#47000
03
#47100
b10 "
b11111111000000000000000001101111 !
13
#47200
03
#47300
b11 "
b1001 '
13
#47400
03
#47500
b100 "
b11111111000000001111111101101111 !
13
#47600
03
#47700
b101 "
b1010 '
13
#47800
03
#47900
b110 "
13
#48000
03
#48100
b111 "
b1011 '
13
#48200
03
#48300
b1000 "
b1111111101101111 !
13
#48400
03
#48500
b1000 '
b1 0
b0 "
13
#48600
03
#48700
b1 "
b110 2
13
#48800
03
#48900
b10 "
b11110 *
b11111111000000001111000000000000 &
13
#49000
03
#49100
b11 "
13
#49200
03
#49300
b1100 )
b0 0
b0 "
13
#49400
03
#49500
b1 "
b1100 '
13
#49600
03
#49700
b10 "
b1111111100110011 !
13
#49800
03
#49900
b11 "
b1101 '
13
