testing/SPI.v
/*

This code is designed to work out an implementation of SPI for the core to access external memory.

NOTE: This code is designed for the M95M01. A 10 MHz clock is expected.

*/

`timescale 1ns/1ns
`default_nettype none

module SPI (
    
    );

    initial begin
        $dumpfile("SPI.vcd");
        $dumpvars(0,SPI);
        #100000 $finish;
    end

    reg clk = 0;

    always #50 clk = !clk;

    //Define instructions
    parameter WREN = 8'b00000110;
    parameter WRDI = 8'b00000100;
    parameter RDSR = 8'b00000101;
    parameter WRSR = 8'b00000001;
    parameter READ = 8'b00000011;
    parameter WRITE = 8'b00000010;

    //Define I/O
    reg SCK = 1;
    reg SI;
    reg SO = 0;
    reg nCS = 1;
    reg nWP = 0;
    reg nHOLD;

    //Define registers
    reg [7:0] SPI_CMD = READ;
    reg [39:0] SPI_BUF = {READ,24'b011010010001001001,8'b1111111};
    reg [31:0] SPI_IN = 0;

    //Define intermediates
    integer i = 0;
    //integer k = 0;
    reg STAGE = 0;

    always @(posedge clk) begin
        case (SPI_CMD)
            WREN : begin
                if (i < 9) begin
                    if (i == 0) begin
                        nCS <= 0;
                        i <= i + 1;
                    end
                    else begin
                        case (STAGE)
                            0 : begin
                                SO <= SPI_BUF[15];
                                STAGE <= 1;
                            end
                            1 : begin
                                i <= i + 1;
                                STAGE <= 0;
                                SPI_BUF <= SPI_BUF << 1;
                            end
                        endcase
                    end
                end
                else begin
                    nCS <= 1;
                end
            end
            WRDI : begin
                if (i < 9) begin
                    if (i == 0) begin
                        nCS <= 0;
                        i <= i + 1;
                    end
                    else begin
                        case (STAGE)
                            0 : begin
                                SO <= SPI_BUF[15];
                                STAGE <= 1;
                            end
                            1 : begin
                                i <= i + 1;
                                STAGE <= 0;
                                SPI_BUF <= SPI_BUF << 1;
                            end
                        endcase
                    end
                end
                else begin
                    nCS <= 1;
                end
            end
            RDSR : begin
                if (i < 24) begin
                    if (i == 0) begin
                        nCS <= 0;
                        i <= i + 1;
                    end
                    else if (i < 9) begin
                        case (STAGE)
                            0 : begin
                                SO <= SPI_BUF[15];
                                STAGE <= 1;
                            end
                            1 : begin
                                i <= i + 1;
                                STAGE <= 0;
                                SPI_BUF <= SPI_BUF << 1;
                            end
                        endcase
                    end
                    else begin
                        case (STAGE)
                            0 : begin
                                SPI_IN[0] <= SI;
                                STAGE <= 1;
                            end
                            1 : begin
                                i <= i + 1;
                                STAGE <= 0;
                                SPI_IN <= SPI_IN << 1;
                            end
                        endcase
                        i <= i + 1;
                    end
                end
                else begin
                    nCS <= 1;
                end
            end
            WRSR : begin
                if (i < 17) begin
                    if (i == 0) begin
                        nCS <= 0;
                        i <= i + 1;
                    end
                    else begin
                        case (STAGE)
                            0 : begin
                                SO <= SPI_BUF[15];
                                STAGE <= 1;
                            end
                            1 : begin
                                i <= i + 1;
                                STAGE <= 0;
                                SPI_BUF <= SPI_BUF << 1;
                            end
                        endcase
                    end
                end
                else begin
                    nCS <= 1;
                end
            end
            READ : begin
                if (i < 101) begin
                    if (i == 0) begin
                        nCS <= 0;
                        i <= i + 1;
                    end
                    else if (i < 34) begin
                        case (STAGE)
                            0 : begin
                                SO <= SPI_BUF[39];
                                STAGE <= 1;
                            end
                            1 : begin
                                i <= i + 1;
                                STAGE <= 0;
                                SPI_BUF <= SPI_BUF << 1;
                            end
                        endcase
                    end
                    else begin
                        case (STAGE)
                            0 : begin
                                SPI_IN[0] <= SI;
                                STAGE <= 1;
                            end
                            1 : begin
                                i <= i + 1;
                                STAGE <= 0;
                                SPI_IN <= SPI_IN << 1;
                            end
                        endcase
                        i <= i + 1;
                    end
                end
                else begin
                    nCS <= 1;
                end
            end
            WRITE : begin
                if (i < 41) begin
                    if (i == 0) begin
                        nCS <= 0;
                        i <= i + 1;
                    end
                    else begin
                        case (STAGE)
                            0 : begin
                                SO <= SPI_BUF[39];
                                STAGE <= 1;
                            end
                            1 : begin
                                i <= i + 1;
                                STAGE <= 0;
                                SPI_BUF <= SPI_BUF << 1;
                            end
                        endcase
                    end
                end
                else begin
                    nCS <= 1;
                end
            end
            default : begin
            end
        endcase
        /*if (k < 9) begin
            if (k == 0) begin
                nCS <= 0;
                k <= k + 1;
            end
            else begin
                case (STAGE)
                    0 : begin
                        SO <= SPI_CMD[7];
                        STAGE <= 1;
                    end
                    1 : begin
                        k <= k + 1; 
                        STAGE <= 0;
                        SPI_CMD <= SPI_CMD << 1;
                    end
                endcase
            end
        end
        else begin
            nCS <= 1;
        end*/
    end
    always @(negedge clk) begin
        SCK <= !SCK;
    end
endmodule

testing/SPI.vcd
$date
	Sun Apr 11 17:14:43 2021
$end
$version
	Icarus Verilog
$end
$timescale
	1ns
$end
$scope module SPI $end
$var reg 1 ! SCK $end
$var reg 1 " SI $end
$var reg 1 # SO $end
$var reg 40 $ SPI_BUF [39:0] $end
$var reg 8 % SPI_CMD [7:0] $end
$var reg 32 & SPI_IN [31:0] $end
$var reg 1 ' STAGE $end
$var reg 1 ( clk $end
$var reg 1 ) nCS $end
$var reg 1 * nWP $end
$var integer 32 + i [31:0] $end
$upscope $end
$enddefinitions $end
#0
$dumpvars
b0 +
0*
1)
0(
0'
b0 &
b11 %
b1100000001101001000100100101111111 $
0#
x"
1!
$end
#50
b1 +
0)
1(
#100
0!
0(
#150
1'
1(
#200
1!
0(
#250
b11000000011010010001001001011111110 $
0'
b10 +
1(
#300
0!
0(
#350
1'
1(
#400
1!
0(
#450
b110000000110100100010010010111111100 $
0'
b11 +
1(
#500
0!
0(
#550
1'
1(
#600
1!
0(
#650
b1100000001101001000100100101111111000 $
0'
b100 +
1(
#700
0!
0(
#750
1'
1(
#800
1!
0(
#850
b11000000011010010001001001011111110000 $
0'
b101 +
1(
#900
0!
0(
#950
1'
1(
#1000
1!
0(
#1050
b110000000110100100010010010111111100000 $
0'
b110 +
1(
#1100
0!
0(
#1150
1'
1(
#1200
1!
0(
#1250
b1100000001101001000100100101111111000000 $
0'
b111 +
1(
#1300
0!
0(
#1350
1'
1#
1(
#1400
1!
0(
#1450
b1000000011010010001001001011111110000000 $
0'
b1000 +
1(
#1500
0!
0(
#1550
1'
1(
#1600
1!
0(
#1650
b110100100010010010111111100000000 $
0'
b1001 +
1(
#1700
0!
0(
#1750
1'
0#
1(
#1800
1!
0(
#1850
b1101001000100100101111111000000000 $
0'
b1010 +
1(
#1900
0!
0(
#1950
1'
1(
#2000
1!
0(
#2050
b11010010001001001011111110000000000 $
0'
b1011 +
1(
#2100
0!
0(
#2150
1'
1(
#2200
1!
0(
#2250
b110100100010010010111111100000000000 $
0'
b1100 +
1(
#2300
0!
0(
#2350
1'
1(
#2400
1!
0(
#2450
b1101001000100100101111111000000000000 $
0'
b1101 +
1(
#2500
0!
0(
#2550
1'
1(
#2600
1!
0(
#2650
b11010010001001001011111110000000000000 $
0'
b1110 +
1(
#2700
0!
0(
#2750
1'
1(
#2800
1!
0(
#2850
b110100100010010010111111100000000000000 $
0'
b1111 +
1(
#2900
0!
0(
#2950
1'
1(
#3000
1!
0(
#3050
b1101001000100100101111111000000000000000 $
0'
b10000 +
1(
#3100
0!
0(
#3150
1'
1#
1(
#3200
1!
0(
#3250
b1010010001001001011111110000000000000000 $
0'
b10001 +
1(
#3300
0!
0(
#3350
1'
1(
#3400
1!
0(
#3450
b100100010010010111111100000000000000000 $
0'
b10010 +
1(
#3500
0!
0(
#3550
1'
0#
1(
#3600
1!
0(
#3650
b1001000100100101111111000000000000000000 $
0'
b10011 +
1(
#3700
0!
0(
#3750
1'
1#
1(
#3800
1!
0(
#3850
b10001001001011111110000000000000000000 $
0'
b10100 +
1(
#3900
0!
0(
#3950
1'
0#
1(
#4000
1!
0(
#4050
b100010010010111111100000000000000000000 $
0'
b10101 +
1(
#4100
0!
0(
#4150
1'
1(
#4200
1!
0(
#4250
b1000100100101111111000000000000000000000 $
0'
b10110 +
1(
#4300
0!
0(
#4350
1'
1#
1(
#4400
1!
0(
#4450
b1001001011111110000000000000000000000 $
0'
b10111 +
1(
#4500
0!
0(
#4550
1'
0#
1(
#4600
1!
0(
#4650
b10010010111111100000000000000000000000 $
0'
b11000 +
1(
#4700
0!
0(
#4750
1'
1(
#4800
1!
0(
#4850
b100100101111111000000000000000000000000 $
0'
b11001 +
1(
#4900
0!
0(
#4950
1'
1(
#5000
1!
0(
#5050
b1001001011111110000000000000000000000000 $
0'
b11010 +
1(
#5100
0!
0(
#5150
1'
1#
1(
#5200
1!
0(
#5250
b10010111111100000000000000000000000000 $
0'
b11011 +
1(
#5300
0!
0(
#5350
1'
0#
1(
#5400
1!
0(
#5450
b100101111111000000000000000000000000000 $
0'
b11100 +
1(
#5500
0!
0(
#5550
1'
1(
#5600
1!
0(
#5650
b1001011111110000000000000000000000000000 $
0'
b11101 +
1(
#5700
0!
0(
#5750
1'
1#
1(
#5800
1!
0(
#5850
b10111111100000000000000000000000000000 $
0'
b11110 +
1(
#5900
0!
0(
#5950
1'
0#
1(
#6000
1!
0(
#6050
b101111111000000000000000000000000000000 $
0'
b11111 +
1(
#6100
0!
0(
#6150
1'
1(
#6200
1!
0(
#6250
b1011111110000000000000000000000000000000 $
0'
b100000 +
1(
#6300
0!
0(
#6350
1'
1#
1(
#6400
1!
0(
#6450
b111111100000000000000000000000000000000 $
0'
b100001 +
1(
#6500
0!
0(
#6550
1'
0#
1(
#6600
1!
0(
#6650
b1111111000000000000000000000000000000000 $
0'
b100010 +
1(
#6700
0!
0(
#6750
b100011 +
1'
b0x &
1(
#6800
1!
0(
#6850
b0x0 &
0'
b100100 +
1(
#6900
0!
0(
#6950
b100101 +
1'
b0xx &
1(
#7000
1!
0(
#7050
b0xx0 &
0'
b100110 +
1(
#7100
0!
0(
#7150
b100111 +
1'
b0xxx &
1(
#7200
1!
0(
#7250
b0xxx0 &
0'
b101000 +
1(
#7300
0!
0(
#7350
b101001 +
1'
b0xxxx &
1(
#7400
1!
0(
#7450
b0xxxx0 &
0'
b101010 +
1(
#7500
0!
0(
#7550
b101011 +
1'
b0xxxxx &
1(
#7600
1!
0(
#7650
b0xxxxx0 &
0'
b101100 +
1(
#7700
0!
0(
#7750
b101101 +
1'
b0xxxxxx &
1(
#7800
1!
0(
#7850
b0xxxxxx0 &
0'
b101110 +
1(
#7900
0!
0(
#7950
b101111 +
1'
b0xxxxxxx &
1(
#8000
1!
0(
#8050
b0xxxxxxx0 &
0'
b110000 +
1(
#8100
0!
0(
#8150
b110001 +
1'
b0xxxxxxxx &
1(
#8200
1!
0(
#8250
b0xxxxxxxx0 &
0'
b110010 +
1(
#8300
0!
0(
#8350
b110011 +
1'
b0xxxxxxxxx &
1(
#8400
1!
0(
#8450
b0xxxxxxxxx0 &
0'
b110100 +
1(
#8500
0!
0(
#8550
b110101 +
1'
b0xxxxxxxxxx &
1(
#8600
1!
0(
#8650
b0xxxxxxxxxx0 &
0'
b110110 +
1(
#8700
0!
0(
#8750
b110111 +
1'
b0xxxxxxxxxxx &
1(
#8800
1!
0(
#8850
b0xxxxxxxxxxx0 &
0'
b111000 +
1(
#8900
0!
0(
#8950
b111001 +
1'
b0xxxxxxxxxxxx &
1(
#9000
1!
0(
#9050
b0xxxxxxxxxxxx0 &
0'
b111010 +
1(
#9100
0!
0(
#9150
b111011 +
1'
b0xxxxxxxxxxxxx &
1(
#9200
1!
0(
#9250
b0xxxxxxxxxxxxx0 &
0'
b111100 +
1(
#9300
0!
0(
#9350
b111101 +
1'
b0xxxxxxxxxxxxxx &
1(
#9400
1!
0(
#9450
b0xxxxxxxxxxxxxx0 &
0'
b111110 +
1(
#9500
0!
0(
#9550
b111111 +
1'
b0xxxxxxxxxxxxxxx &
1(
#9600
1!
0(
#9650
b0xxxxxxxxxxxxxxx0 &
0'
b1000000 +
1(
#9700
0!
0(
#9750
b1000001 +
1'
b0xxxxxxxxxxxxxxxx &
1(
#9800
1!
0(
#9850
b0xxxxxxxxxxxxxxxx0 &
0'
b1000010 +
1(
#9900
0!
0(
#9950
b1000011 +
1'
b0xxxxxxxxxxxxxxxxx &
1(
#10000
1!
0(
#10050
b0xxxxxxxxxxxxxxxxx0 &
0'
b1000100 +
1(
#10100
0!
0(
#10150
b1000101 +
1'
b0xxxxxxxxxxxxxxxxxx &
1(
#10200
1!
0(
#10250
b0xxxxxxxxxxxxxxxxxx0 &
0'
b1000110 +
1(
#10300
0!
0(
#10350
b1000111 +
1'
b0xxxxxxxxxxxxxxxxxxx &
1(
#10400
1!
0(
#10450
b0xxxxxxxxxxxxxxxxxxx0 &
0'
b1001000 +
1(
#10500
0!
0(
#10550
b1001001 +
1'
b0xxxxxxxxxxxxxxxxxxxx &
1(
#10600
1!
0(
#10650
b0xxxxxxxxxxxxxxxxxxxx0 &
0'
b1001010 +
1(
#10700
0!
0(
#10750
b1001011 +
1'
b0xxxxxxxxxxxxxxxxxxxxx &
1(
#10800
1!
0(
#10850
b0xxxxxxxxxxxxxxxxxxxxx0 &
0'
b1001100 +
1(
#10900
0!
0(
#10950
b1001101 +
1'
b0xxxxxxxxxxxxxxxxxxxxxx &
1(
#11000
1!
0(
#11050
b0xxxxxxxxxxxxxxxxxxxxxx0 &
0'
b1001110 +
1(
#11100
0!
0(
#11150
b1001111 +
1'
b0xxxxxxxxxxxxxxxxxxxxxxx &
1(
#11200
1!
0(
#11250
b0xxxxxxxxxxxxxxxxxxxxxxx0 &
0'
b1010000 +
1(
#11300
0!
0(
#11350
b1010001 +
1'
b0xxxxxxxxxxxxxxxxxxxxxxxx &
1(
#11400
1!
0(
#11450
b0xxxxxxxxxxxxxxxxxxxxxxxx0 &
0'
b1010010 +
1(
#11500
0!
0(
#11550
b1010011 +
1'
b0xxxxxxxxxxxxxxxxxxxxxxxxx &
1(
#11600
1!
0(
#11650
b0xxxxxxxxxxxxxxxxxxxxxxxxx0 &
0'
b1010100 +
1(
#11700
0!
0(
#11750
b1010101 +
1'
b0xxxxxxxxxxxxxxxxxxxxxxxxxx &
1(
#11800
1!
0(
#11850
b0xxxxxxxxxxxxxxxxxxxxxxxxxx0 &
0'
b1010110 +
1(
#11900
0!
0(
#11950
b1010111 +
1'
b0xxxxxxxxxxxxxxxxxxxxxxxxxxx &
1(
#12000
1!
0(
#12050
b0xxxxxxxxxxxxxxxxxxxxxxxxxxx0 &
0'
b1011000 +
1(
#12100
0!
0(
#12150
b1011001 +
1'
b0xxxxxxxxxxxxxxxxxxxxxxxxxxxx &
1(
#12200
1!
0(
#12250
b0xxxxxxxxxxxxxxxxxxxxxxxxxxxx0 &
0'
b1011010 +
1(
#12300
0!
0(
#12350
b1011011 +
1'
b0xxxxxxxxxxxxxxxxxxxxxxxxxxxxx &
1(
#12400
1!
0(
#12450
b0xxxxxxxxxxxxxxxxxxxxxxxxxxxxx0 &
0'
b1011100 +
1(
#12500
0!
0(
#12550
b1011101 +
1'
b0xxxxxxxxxxxxxxxxxxxxxxxxxxxxxx &
1(
#12600
1!
0(
#12650
b0xxxxxxxxxxxxxxxxxxxxxxxxxxxxxx0 &
0'
b1011110 +
1(
#12700
0!
0(
#12750
b1011111 +
1'
b0xxxxxxxxxxxxxxxxxxxxxxxxxxxxxxx &
1(
#12800
1!
0(
#12850
bx0 &
0'
b1100000 +
1(
#12900
0!
0(
#12950
b1100001 +
1'
bx &
1(
#13000
1!
0(
#13050
bx0 &
0'
b1100010 +
1(
#13100
0!
0(
#13150
b1100011 +
1'
bx &
1(
#13200
1!
0(
#13250
bx0 &
0'
b1100100 +
1(
#13300
0!
0(
#13350
b1100101 +
1'
bx &
1(
#13400
1!
0(
#13450
1)
1(
#13500
0!
0(
#13550
1(
#13600
1!
0(
#13650
1(
#13700
0!
0(
#13750
1(
#13800
1!
0(
#13850
1(
#13900
0!
0(
#13950
1(
#14000
1!
0(
#14050
1(
#14100
0!
0(
#14150
1(
#14200
1!
0(
#14250
1(
#14300
0!
0(
#14350
1(
#14400
1!
0(
#14450
1(
#14500
0!
0(
#14550
1(
#14600
1!
0(
#14650
1(
#14700
0!
0(
#14750
1(
#14800
1!
0(
#14850
1(
#14900
0!
0(
#14950
1(
#15000
1!
0(
#15050
1(
#15100
0!
0(
#15150
1(
#15200
1!
0(
#15250
1(
#15300
0!
0(
#15350
1(
#15400
1!
0(
#15450
1(
#15500
0!
0(
#15550
1(
#15600
1!
0(
#15650
1(
#15700
0!
0(
#15750
1(
#15800
1!
0(
#15850
1(
#15900
0!
0(
#15950
1(
#16000
1!
0(
#16050
1(
#16100
0!
0(
#16150
1(
#16200
1!
0(
#16250
1(
#16300
0!
0(
#16350
1(
#16400
1!
0(
#16450
1(
#16500
0!
0(
#16550
1(
#16600
1!
0(
#16650
1(
#16700
0!
0(
#16750
1(
#16800
1!
0(
#16850
1(
#16900
0!
0(
#16950
1(
#17000
1!
0(
#17050
1(
#17100
0!
0(
#17150
1(
#17200
1!
0(
#17250
1(
#17300
0!
0(
#17350
1(
#17400
1!
0(
#17450
1(
#17500
0!
0(
#17550
1(
#17600
1!
0(
#17650
1(
#17700
0!
0(
#17750
1(
#17800
1!
0(
#17850
1(
#17900
0!
0(
#17950
1(
#18000
1!
0(
#18050
1(
#18100
0!
0(
#18150
1(
#18200
1!
0(
#18250
1(
#18300
0!
0(
#18350
1(
#18400
1!
0(
#18450
1(
#18500
0!
0(
#18550
1(
#18600
1!
0(
#18650
1(
#18700
0!
0(
#18750
1(
#18800
1!
0(
#18850
1(
#18900
0!
0(
#18950
1(
#19000
1!
0(
#19050
1(
#19100
0!
0(
#19150
1(
#19200
1!
0(
#19250
1(
#19300
0!
0(
#19350
1(
#19400
1!
0(
#19450
1(
#19500
0!
0(
#19550
1(
#19600
1!
0(
#19650
1(
#19700
0!
0(
#19750
1(
#19800
1!
0(
#19850
1(
#19900
0!
0(
#19950
1(
#20000
1!
0(
#20050
1(
#20100
0!
0(
#20150
1(
#20200
1!
0(
#20250
1(
#20300
0!
0(
#20350
1(
#20400
1!
0(
#20450
1(
#20500
0!
0(
#20550
1(
#20600
1!
0(
#20650
1(
#20700
0!
0(
#20750
1(
#20800
1!
0(
#20850
1(
#20900
0!
0(
#20950
1(
#21000
1!
0(
#21050
1(
#21100
0!
0(
#21150
1(
#21200
1!
0(
#21250
1(
#21300
0!
0(
#21350
1(
#21400
1!
0(
#21450
1(
#21500
0!
0(
#21550
1(
#21600
1!
0(
#21650
1(
#21700
0!
0(
#21750
1(
#21800
1!
0(
#21850
1(
#21900
0!
0(
#21950
1(
#22000
1!
0(
#22050
1(
#22100
0!
0(
#22150
1(
#22200
1!
0(
#22250
1(
#22300
0!
0(
#22350
1(
#22400
1!
0(
#22450
1(
#22500
0!
0(
#22550
1(
#22600
1!
0(
#22650
1(
#22700
0!
0(
#22750
1(
#22800
1!
0(
#22850
1(
#22900
0!
0(
#22950
1(
#23000
1!
0(
#23050
1(
#23100
0!
0(
#23150
1(
#23200
1!
0(
#23250
1(
#23300
0!
0(
#23350
1(
#23400
1!
0(
#23450
1(
#23500
0!
0(
#23550
1(
#23600
1!
0(
#23650
1(
#23700
0!
0(
#23750
1(
#23800
1!
0(
#23850
1(
#23900
0!
0(
#23950
1(
#24000
1!
0(
#24050
1(
#24100
0!
0(
#24150
1(
#24200
1!
0(
#24250
1(
#24300
0!
0(
#24350
1(
#24400
1!
0(
#24450
1(
#24500
0!
0(
#24550
1(
#24600
1!
0(
#24650
1(
#24700
0!
0(
#24750
1(
#24800
1!
0(
#24850
1(
#24900
0!
0(
#24950
1(
#25000
1!
0(
#25050
1(
#25100
0!
0(
#25150
1(
#25200
1!
0(
#25250
1(
#25300
0!
0(
#25350
1(
#25400
1!
0(
#25450
1(
#25500
0!
0(
#25550
1(
#25600
1!
0(
#25650
1(
#25700
0!
0(
#25750
1(
#25800
1!
0(
#25850
1(
#25900
0!
0(
#25950
1(
#26000
1!
0(
#26050
1(
#26100
0!
0(
#26150
1(
#26200
1!
0(
#26250
1(
#26300
0!
0(
#26350
1(
#26400
1!
0(
#26450
1(
#26500
0!
0(
#26550
1(
#26600
1!
0(
#26650
1(
#26700
0!
0(
#26750
1(
#26800
1!
0(
#26850
1(
#26900
0!
0(
#26950
1(
#27000
1!
0(
#27050
1(
#27100
0!
0(
#27150
1(
#27200
1!
0(
#27250
1(
#27300
0!
0(
#27350
1(
#27400
1!
0(
#27450
1(
#27500
0!
0(
#27550
1(
#27600
1!
0(
#27650
1(
#27700
0!
0(
#27750
1(
#27800
1!
0(
#27850
1(
#27900
0!
0(
#27950
1(
#28000
1!
0(
#28050
1(
#28100
0!
0(
#28150
1(
#28200
1!
0(
#28250
1(
#28300
0!
0(
#28350
1(
#28400
1!
0(
#28450
1(
#28500
0!
0(
#28550
1(
#28600
1!
0(
#28650
1(
#28700
0!
0(
#28750
1(
#28800
1!
0(
#28850
1(
#28900
0!
0(
#28950
1(
#29000
1!
0(
#29050
1(
#29100
0!
0(
#29150
1(
#29200
1!
0(
#29250
1(
#29300
0!
0(
#29350
1(
#29400
1!
0(
#29450
1(
#29500
0!
0(
#29550
1(
#29600
1!
0(
#29650
1(
#29700
0!
0(
#29750
1(
#29800
1!
0(
#29850
1(
#29900
0!
0(
#29950
1(
#30000
1!
0(
#30050
1(
#30100
0!
0(
#30150
1(
#30200
1!
0(
#30250
1(
#30300
0!
0(
#30350
1(
#30400
1!
0(
#30450
1(
#30500
0!
0(
#30550
1(
#30600
1!
0(
#30650
1(
#30700
0!
0(
#30750
1(
#30800
1!
0(
#30850
1(
#30900
0!
0(
#30950
1(
#31000
1!
0(
#31050
1(
#31100
0!
0(
#31150
1(
#31200
1!
0(
#31250
1(
#31300
0!
0(
#31350
1(
#31400
1!
0(
#31450
1(
#31500
0!
0(
#31550
1(
#31600
1!
0(
#31650
1(
#31700
0!
0(
#31750
1(
#31800
1!
0(
#31850
1(
#31900
0!
0(
#31950
1(
#32000
1!
0(
#32050
1(
#32100
0!
0(
#32150
1(
#32200
1!
0(
#32250
1(
#32300
0!
0(
#32350
1(
#32400
1!
0(
#32450
1(
#32500
0!
0(
#32550
1(
#32600
1!
0(
#32650
1(
#32700
0!
0(
#32750
1(
#32800
1!
0(
#32850
1(
#32900
0!
0(
#32950
1(
#33000
1!
0(
#33050
1(
#33100
0!
0(
#33150
1(
#33200
1!
0(
#33250
1(
#33300
0!
0(
#33350
1(
#33400
1!
0(
#33450
1(
#33500
0!
0(
#33550
1(
#33600
1!
0(
#33650
1(
#33700
0!
0(
#33750
1(
#33800
1!
0(
#33850
1(
#33900
0!
0(
#33950
1(
#34000
1!
0(
#34050
1(
#34100
0!
0(
#34150
1(
#34200
1!
0(
#34250
1(
#34300
0!
0(
#34350
1(
#34400
1!
0(
#34450
1(
#34500
0!
0(
#34550
1(
#34600
1!
0(
#34650
1(
#34700
0!
0(
#34750
1(
#34800
1!
0(
#34850
1(
#34900
0!
0(
#34950
1(
#35000
1!
0(
#35050
1(
#35100
0!
0(
#35150
1(
#35200
1!
0(
#35250
1(
#35300
0!
0(
#35350
1(
#35400
1!
0(
#35450
1(
#35500
0!
0(
#35550
1(
#35600
1!
0(
#35650
1(
#35700
0!
0(
#35750
1(
#35800
1!
0(
#35850
1(
#35900
0!
0(
#35950
1(
#36000
1!
0(
#36050
1(
#36100
0!
0(
#36150
1(
#36200
1!
0(
#36250
1(
#36300
0!
0(
#36350
1(
#36400
1!
0(
#36450
1(
#36500
0!
0(
#36550
1(
#36600
1!
0(
#36650
1(
#36700
0!
0(
#36750
1(
#36800
1!
0(
#36850
1(
#36900
0!
0(
#36950
1(
#37000
1!
0(
#37050
1(
#37100
0!
0(
#37150
1(
#37200
1!
0(
#37250
1(
#37300
0!
0(
#37350
1(
#37400
1!
0(
#37450
1(
#37500
0!
0(
#37550
1(
#37600
1!
0(
#37650
1(
#37700
0!
0(
#37750
1(
#37800
1!
0(
#37850
1(
#37900
0!
0(
#37950
1(
#38000
1!
0(
#38050
1(
#38100
0!
0(
#38150
1(
#38200
1!
0(
#38250
1(
#38300
0!
0(
#38350
1(
#38400
1!
0(
#38450
1(
#38500
0!
0(
#38550
1(
#38600
1!
0(
#38650
1(
#38700
0!
0(
#38750
1(
#38800
1!
0(
#38850
1(
#38900
0!
0(
#38950
1(
#39000
1!
0(
#39050
1(
#39100
0!
0(
#39150
1(
#39200
1!
0(
#39250
1(
#39300
0!
0(
#39350
1(
#39400
1!
0(
#39450
1(
#39500
0!
0(
#39550
1(
#39600
1!
0(
#39650
1(
#39700
0!
0(
#39750
1(
#39800
1!
0(
#39850
1(
#39900
0!
0(
#39950
1(
#40000
1!
0(
#40050
1(
#40100
0!
0(
#40150
1(
#40200
1!
0(
#40250
1(
#40300
0!
0(
#40350
1(
#40400
1!
0(
#40450
1(
#40500
0!
0(
#40550
1(
#40600
1!
0(
#40650
1(
#40700
0!
0(
#40750
1(
#40800
1!
0(
#40850
1(
#40900
0!
0(
#40950
1(
#41000
1!
0(
#41050
1(
#41100
0!
0(
#41150
1(
#41200
1!
0(
#41250
1(
#41300
0!
0(
#41350
1(
#41400
1!
0(
#41450
1(
#41500
0!
0(
#41550
1(
#41600
1!
0(
#41650
1(
#41700
0!
0(
#41750
1(
#41800
1!
0(
#41850
1(
#41900
0!
0(
#41950
1(
#42000
1!
0(
#42050
1(
#42100
0!
0(
#42150
1(
#42200
1!
0(
#42250
1(
#42300
0!
0(
#42350
1(
#42400
1!
0(
#42450
1(
#42500
0!
0(
#42550
1(
#42600
1!
0(
#42650
1(
#42700
0!
0(
#42750
1(
#42800
1!
0(
#42850
1(
#42900
0!
0(
#42950
1(
#43000
1!
0(
#43050
1(
#43100
0!
0(
#43150
1(
#43200
1!
0(
#43250
1(
#43300
0!
0(
#43350
1(
#43400
1!
0(
#43450
1(
#43500
0!
0(
#43550
1(
#43600
1!
0(
#43650
1(
#43700
0!
0(
#43750
1(
#43800
1!
0(
#43850
1(
#43900
0!
0(
#43950
1(
#44000
1!
0(
#44050
1(
#44100
0!
0(
#44150
1(
#44200
1!
0(
#44250
1(
#44300
0!
0(
#44350
1(
#44400
1!
0(
#44450
1(
#44500
0!
0(
#44550
1(
#44600
1!
0(
#44650
1(
#44700
0!
0(
#44750
1(
#44800
1!
0(
#44850
1(
#44900
0!
0(
#44950
1(
#45000
1!
0(
#45050
1(
#45100
0!
0(
#45150
1(
#45200
1!
0(
#45250
1(
#45300
0!
0(
#45350
1(
#45400
1!
0(
#45450
1(
#45500
0!
0(
#45550
1(
#45600
1!
0(
#45650
1(
#45700
0!
0(
#45750
1(
#45800
1!
0(
#45850
1(
#45900
0!
0(
#45950
1(
#46000
1!
0(
#46050
1(
#46100
0!
0(
#46150
1(
#46200
1!
0(
#46250
1(
#46300
0!
0(
#46350
1(
#46400
1!
0(
#46450
1(
#46500
0!
0(
#46550
1(
#46600
1!
0(
#46650
1(
#46700
0!
0(
#46750
1(
#46800
1!
0(
#46850
1(
#46900
0!
0(
#46950
1(
#47000
1!
0(
#47050
1(
#47100
0!
0(
#47150
1(
#47200
1!
0(
#47250
1(
#47300
0!
0(
#47350
1(
#47400
1!
0(
#47450
1(
#47500
0!
0(
#47550
1(
#47600
1!
0(
#47650
1(
#47700
0!
0(
#47750
1(
#47800
1!
0(
#47850
1(
#47900
0!
0(
#47950
1(
#48000
1!
0(
#48050
1(
#48100
0!
0(
#48150
1(
#48200
1!
0(
#48250
1(
#48300
0!
0(
#48350
1(
#48400
1!
0(
#48450
1(
#48500
0!
0(
#48550
1(
#48600
1!
0(
#48650
1(
#48700
0!
0(
#48750
1(
#48800
1!
0(
#48850
1(
#48900
0!
0(
#48950
1(
#49000
1!
0(
#49050
1(
#49100
0!
0(
#49150
1(
#49200
1!
0(
#49250
1(
#49300
0!
0(
#49350
1(
#49400
1!
0(
#49450
1(
#49500
0!
0(
#49550
1(
#49600
1!
0(
#49650
1(
#49700
0!
0(
#49750
1(
#49800
1!
0(
#49850
1(
#49900
0!
0(
#49950
1(
#50000
1!
0(
#50050
1(
#50100
0!
0(
#50150
1(
#50200
1!
0(
#50250
1(
#50300
0!
0(
#50350
1(
#50400
1!
0(
#50450
1(
#50500
0!
0(
#50550
1(
#50600
1!
0(
#50650
1(
#50700
0!
0(
#50750
1(
#50800
1!
0(
#50850
1(
#50900
0!
0(
#50950
1(
#51000
1!
0(
#51050
1(
#51100
0!
0(
#51150
1(
#51200
1!
0(
#51250
1(
#51300
0!
0(
#51350
1(
#51400
1!
0(
#51450
1(
#51500
0!
0(
#51550
1(
#51600
1!
0(
#51650
1(
#51700
0!
0(
#51750
1(
#51800
1!
0(
#51850
1(
#51900
0!
0(
#51950
1(
#52000
1!
0(
#52050
1(
#52100
0!
0(
#52150
1(
#52200
1!
0(
#52250
1(
#52300
0!
0(
#52350
1(
#52400
1!
0(
#52450
1(
#52500
0!
0(
#52550
1(
#52600
1!
0(
#52650
1(
#52700
0!
0(
#52750
1(
#52800
1!
0(
#52850
1(
#52900
0!
0(
#52950
1(
#53000
1!
0(
#53050
1(
#53100
0!
0(
#53150
1(
#53200
1!
0(
#53250
1(
#53300
0!
0(
#53350
1(
#53400
1!
0(
#53450
1(
#53500
0!
0(
#53550
1(
#53600
1!
0(
#53650
1(
#53700
0!
0(
#53750
1(
#53800
1!
0(
#53850
1(
#53900
0!
0(
#53950
1(
#54000
1!
0(
#54050
1(
#54100
0!
0(
#54150
1(
#54200
1!
0(
#54250
1(
#54300
0!
0(
#54350
1(
#54400
1!
0(
#54450
1(
#54500
0!
0(
#54550
1(
#54600
1!
0(
#54650
1(
#54700
0!
0(
#54750
1(
#54800
1!
0(
#54850
1(
#54900
0!
0(
#54950
1(
#55000
1!
0(
#55050
1(
#55100
0!
0(
#55150
1(
#55200
1!
0(
#55250
1(
#55300
0!
0(
#55350
1(
#55400
1!
0(
#55450
1(
#55500
0!
0(
#55550
1(
#55600
1!
0(
